package com.threatmetrix.TrustDefenderMobile;

class PutXML
  implements Runnable
{
  private static final String TAG = StringUtils.getLogTag(PutXML.class);
  private String fp_server = null;
  private String org_id = null;
  private String session_id = null;
  private int timeout = 10000;
  private String w = null;
  
  public PutXML(String paramString1, String paramString2, String paramString3, String paramString4, int paramInt)
  {
    fp_server = paramString1;
    org_id = paramString2;
    session_id = paramString3;
    w = paramString4;
    timeout = paramInt;
  }
  
  /* Error */
  public void run()
  {
    // Byte code:
    //   0: aconst_null
    //   1: astore 13
    //   3: aconst_null
    //   4: astore 5
    //   6: aconst_null
    //   7: astore 12
    //   9: aconst_null
    //   10: astore 10
    //   12: aconst_null
    //   13: astore 4
    //   15: aconst_null
    //   16: astore 11
    //   18: aconst_null
    //   19: astore 7
    //   21: aconst_null
    //   22: astore 9
    //   24: aconst_null
    //   25: astore_3
    //   26: aconst_null
    //   27: astore 6
    //   29: aconst_null
    //   30: astore 8
    //   32: new 46	java/net/Socket
    //   35: dup
    //   36: aload_0
    //   37: getfield 31	com/threatmetrix/TrustDefenderMobile/PutXML:fp_server	Ljava/lang/String;
    //   40: sipush 8080
    //   43: invokespecial 49	java/net/Socket:<init>	(Ljava/lang/String;I)V
    //   46: astore_2
    //   47: aload_2
    //   48: aload_0
    //   49: getfield 39	com/threatmetrix/TrustDefenderMobile/PutXML:timeout	I
    //   52: invokevirtual 53	java/net/Socket:setSoTimeout	(I)V
    //   55: new 55	java/io/BufferedWriter
    //   58: dup
    //   59: new 57	java/io/PrintWriter
    //   62: dup
    //   63: aload_2
    //   64: invokevirtual 61	java/net/Socket:getOutputStream	()Ljava/io/OutputStream;
    //   67: invokespecial 64	java/io/PrintWriter:<init>	(Ljava/io/OutputStream;)V
    //   70: invokespecial 67	java/io/BufferedWriter:<init>	(Ljava/io/Writer;)V
    //   73: astore_3
    //   74: new 69	java/io/BufferedReader
    //   77: dup
    //   78: new 71	java/io/InputStreamReader
    //   81: dup
    //   82: aload_2
    //   83: invokevirtual 75	java/net/Socket:getInputStream	()Ljava/io/InputStream;
    //   86: invokespecial 78	java/io/InputStreamReader:<init>	(Ljava/io/InputStream;)V
    //   89: invokespecial 81	java/io/BufferedReader:<init>	(Ljava/io/Reader;)V
    //   92: astore 4
    //   94: aload_3
    //   95: new 83	java/lang/StringBuilder
    //   98: dup
    //   99: invokespecial 84	java/lang/StringBuilder:<init>	()V
    //   102: ldc 86
    //   104: invokevirtual 90	java/lang/StringBuilder:append	(Ljava/lang/String;)Ljava/lang/StringBuilder;
    //   107: aload_0
    //   108: getfield 35	com/threatmetrix/TrustDefenderMobile/PutXML:session_id	Ljava/lang/String;
    //   111: invokevirtual 90	java/lang/StringBuilder:append	(Ljava/lang/String;)Ljava/lang/StringBuilder;
    //   114: ldc 92
    //   116: invokevirtual 90	java/lang/StringBuilder:append	(Ljava/lang/String;)Ljava/lang/StringBuilder;
    //   119: aload_0
    //   120: getfield 33	com/threatmetrix/TrustDefenderMobile/PutXML:org_id	Ljava/lang/String;
    //   123: invokevirtual 90	java/lang/StringBuilder:append	(Ljava/lang/String;)Ljava/lang/StringBuilder;
    //   126: ldc 94
    //   128: invokevirtual 90	java/lang/StringBuilder:append	(Ljava/lang/String;)Ljava/lang/StringBuilder;
    //   131: aload_0
    //   132: getfield 37	com/threatmetrix/TrustDefenderMobile/PutXML:w	Ljava/lang/String;
    //   135: invokevirtual 90	java/lang/StringBuilder:append	(Ljava/lang/String;)Ljava/lang/StringBuilder;
    //   138: ldc 96
    //   140: invokevirtual 90	java/lang/StringBuilder:append	(Ljava/lang/String;)Ljava/lang/StringBuilder;
    //   143: invokevirtual 100	java/lang/StringBuilder:toString	()Ljava/lang/String;
    //   146: invokevirtual 104	java/io/BufferedWriter:write	(Ljava/lang/String;)V
    //   149: aload_3
    //   150: invokevirtual 107	java/io/BufferedWriter:flush	()V
    //   153: aload 4
    //   155: invokevirtual 111	java/io/BufferedReader:read	()I
    //   158: iconst_m1
    //   159: if_icmpeq +35 -> 194
    //   162: iconst_0
    //   163: istore_1
    //   164: iload_1
    //   165: bipush 15
    //   167: if_icmpge +21 -> 188
    //   170: aload_3
    //   171: iconst_1
    //   172: newarray <illegal type>
    //   174: dup
    //   175: iconst_0
    //   176: iconst_0
    //   177: castore
    //   178: invokevirtual 114	java/io/BufferedWriter:write	([C)V
    //   181: iload_1
    //   182: iconst_1
    //   183: iadd
    //   184: istore_1
    //   185: goto -21 -> 164
    //   188: aload 4
    //   190: invokevirtual 111	java/io/BufferedReader:read	()I
    //   193: pop
    //   194: getstatic 24	com/threatmetrix/TrustDefenderMobile/PutXML:TAG	Ljava/lang/String;
    //   197: ldc 116
    //   199: invokestatic 122	android/util/Log:d	(Ljava/lang/String;Ljava/lang/String;)I
    //   202: pop
    //   203: aload_2
    //   204: ifnull +374 -> 578
    //   207: aload_2
    //   208: invokevirtual 125	java/net/Socket:close	()V
    //   211: aload_3
    //   212: ifnull +363 -> 575
    //   215: aload_3
    //   216: invokevirtual 126	java/io/BufferedWriter:close	()V
    //   219: aload 4
    //   221: ifnull +353 -> 574
    //   224: aload 4
    //   226: invokevirtual 127	java/io/BufferedReader:close	()V
    //   229: return
    //   230: astore 6
    //   232: aload 12
    //   234: astore_2
    //   235: aload 8
    //   237: astore_3
    //   238: aload 7
    //   240: astore 4
    //   242: aload_2
    //   243: astore 5
    //   245: getstatic 24	com/threatmetrix/TrustDefenderMobile/PutXML:TAG	Ljava/lang/String;
    //   248: ldc -127
    //   250: aload 6
    //   252: invokestatic 132	android/util/Log:w	(Ljava/lang/String;Ljava/lang/String;Ljava/lang/Throwable;)I
    //   255: pop
    //   256: getstatic 24	com/threatmetrix/TrustDefenderMobile/PutXML:TAG	Ljava/lang/String;
    //   259: ldc 116
    //   261: invokestatic 122	android/util/Log:d	(Ljava/lang/String;Ljava/lang/String;)I
    //   264: pop
    //   265: aload_2
    //   266: ifnull +7 -> 273
    //   269: aload_2
    //   270: invokevirtual 125	java/net/Socket:close	()V
    //   273: aload 7
    //   275: ifnull +8 -> 283
    //   278: aload 7
    //   280: invokevirtual 126	java/io/BufferedWriter:close	()V
    //   283: aload 8
    //   285: ifnull -56 -> 229
    //   288: aload 8
    //   290: invokevirtual 127	java/io/BufferedReader:close	()V
    //   293: return
    //   294: astore 6
    //   296: aload 13
    //   298: astore_2
    //   299: aload 10
    //   301: astore 7
    //   303: aload 9
    //   305: astore 8
    //   307: aload 8
    //   309: astore_3
    //   310: aload 7
    //   312: astore 4
    //   314: aload_2
    //   315: astore 5
    //   317: getstatic 24	com/threatmetrix/TrustDefenderMobile/PutXML:TAG	Ljava/lang/String;
    //   320: ldc -122
    //   322: aload 6
    //   324: invokestatic 132	android/util/Log:w	(Ljava/lang/String;Ljava/lang/String;Ljava/lang/Throwable;)I
    //   327: pop
    //   328: getstatic 24	com/threatmetrix/TrustDefenderMobile/PutXML:TAG	Ljava/lang/String;
    //   331: ldc 116
    //   333: invokestatic 122	android/util/Log:d	(Ljava/lang/String;Ljava/lang/String;)I
    //   336: pop
    //   337: aload_2
    //   338: ifnull +7 -> 345
    //   341: aload_2
    //   342: invokevirtual 125	java/net/Socket:close	()V
    //   345: aload 7
    //   347: ifnull +8 -> 355
    //   350: aload 7
    //   352: invokevirtual 126	java/io/BufferedWriter:close	()V
    //   355: aload 8
    //   357: ifnull -128 -> 229
    //   360: aload 8
    //   362: invokevirtual 127	java/io/BufferedReader:close	()V
    //   365: return
    //   366: astore_2
    //   367: getstatic 24	com/threatmetrix/TrustDefenderMobile/PutXML:TAG	Ljava/lang/String;
    //   370: ldc 116
    //   372: invokestatic 122	android/util/Log:d	(Ljava/lang/String;Ljava/lang/String;)I
    //   375: pop
    //   376: aload 5
    //   378: ifnull +8 -> 386
    //   381: aload 5
    //   383: invokevirtual 125	java/net/Socket:close	()V
    //   386: aload 4
    //   388: ifnull +8 -> 396
    //   391: aload 4
    //   393: invokevirtual 126	java/io/BufferedWriter:close	()V
    //   396: aload_3
    //   397: ifnull +7 -> 404
    //   400: aload_3
    //   401: invokevirtual 127	java/io/BufferedReader:close	()V
    //   404: aload_2
    //   405: athrow
    //   406: astore_2
    //   407: goto -196 -> 211
    //   410: astore_2
    //   411: goto -192 -> 219
    //   414: astore_2
    //   415: goto -186 -> 229
    //   418: astore_2
    //   419: goto -146 -> 273
    //   422: astore_2
    //   423: goto -140 -> 283
    //   426: astore_2
    //   427: goto -134 -> 293
    //   430: astore_2
    //   431: goto -86 -> 345
    //   434: astore_2
    //   435: goto -80 -> 355
    //   438: astore_2
    //   439: goto -74 -> 365
    //   442: astore 5
    //   444: goto -58 -> 386
    //   447: astore 4
    //   449: goto -53 -> 396
    //   452: astore_3
    //   453: goto -49 -> 404
    //   456: astore 7
    //   458: aload 6
    //   460: astore_3
    //   461: aload 11
    //   463: astore 4
    //   465: aload_2
    //   466: astore 5
    //   468: aload 7
    //   470: astore_2
    //   471: goto -104 -> 367
    //   474: astore 7
    //   476: aload_3
    //   477: astore 4
    //   479: aload 6
    //   481: astore_3
    //   482: aload_2
    //   483: astore 5
    //   485: aload 7
    //   487: astore_2
    //   488: goto -121 -> 367
    //   491: astore 6
    //   493: aload_3
    //   494: astore 5
    //   496: aload 4
    //   498: astore_3
    //   499: aload 5
    //   501: astore 4
    //   503: aload_2
    //   504: astore 5
    //   506: aload 6
    //   508: astore_2
    //   509: goto -142 -> 367
    //   512: astore 6
    //   514: aload 9
    //   516: astore 8
    //   518: aload 10
    //   520: astore 7
    //   522: goto -215 -> 307
    //   525: astore 6
    //   527: aload 9
    //   529: astore 8
    //   531: aload_3
    //   532: astore 7
    //   534: goto -227 -> 307
    //   537: astore 6
    //   539: aload 4
    //   541: astore 8
    //   543: aload_3
    //   544: astore 7
    //   546: goto -239 -> 307
    //   549: astore 6
    //   551: goto -316 -> 235
    //   554: astore 6
    //   556: aload_3
    //   557: astore 7
    //   559: goto -324 -> 235
    //   562: astore 6
    //   564: aload 4
    //   566: astore 8
    //   568: aload_3
    //   569: astore 7
    //   571: goto -336 -> 235
    //   574: return
    //   575: goto -356 -> 219
    //   578: goto -367 -> 211
    // Local variable table:
    //   start	length	slot	name	signature
    //   0	581	0	this	PutXML
    //   163	22	1	i	int
    //   46	296	2	localObject1	Object
    //   366	39	2	localObject2	Object
    //   406	1	2	localIOException1	java.io.IOException
    //   410	1	2	localIOException2	java.io.IOException
    //   414	1	2	localIOException3	java.io.IOException
    //   418	1	2	localIOException4	java.io.IOException
    //   422	1	2	localIOException5	java.io.IOException
    //   426	1	2	localIOException6	java.io.IOException
    //   430	1	2	localIOException7	java.io.IOException
    //   434	1	2	localIOException8	java.io.IOException
    //   438	28	2	localIOException9	java.io.IOException
    //   470	39	2	localObject3	Object
    //   25	376	3	localObject4	Object
    //   452	1	3	localIOException10	java.io.IOException
    //   460	109	3	localObject5	Object
    //   13	379	4	localObject6	Object
    //   447	1	4	localIOException11	java.io.IOException
    //   463	102	4	localObject7	Object
    //   4	378	5	localObject8	Object
    //   442	1	5	localIOException12	java.io.IOException
    //   466	39	5	localObject9	Object
    //   27	1	6	localObject10	Object
    //   230	21	6	localUnknownHostException1	java.net.UnknownHostException
    //   294	186	6	localIOException13	java.io.IOException
    //   491	16	6	localObject11	Object
    //   512	1	6	localIOException14	java.io.IOException
    //   525	1	6	localIOException15	java.io.IOException
    //   537	1	6	localIOException16	java.io.IOException
    //   549	1	6	localUnknownHostException2	java.net.UnknownHostException
    //   554	1	6	localUnknownHostException3	java.net.UnknownHostException
    //   562	1	6	localUnknownHostException4	java.net.UnknownHostException
    //   19	332	7	localObject12	Object
    //   456	13	7	localObject13	Object
    //   474	12	7	localObject14	Object
    //   520	50	7	localObject15	Object
    //   30	537	8	localObject16	Object
    //   22	506	9	localObject17	Object
    //   10	509	10	localObject18	Object
    //   16	446	11	localObject19	Object
    //   7	226	12	localObject20	Object
    //   1	296	13	localObject21	Object
    // Exception table:
    //   from	to	target	type
    //   32	47	230	java/net/UnknownHostException
    //   32	47	294	java/io/IOException
    //   32	47	366	finally
    //   245	256	366	finally
    //   317	328	366	finally
    //   207	211	406	java/io/IOException
    //   215	219	410	java/io/IOException
    //   224	229	414	java/io/IOException
    //   269	273	418	java/io/IOException
    //   278	283	422	java/io/IOException
    //   288	293	426	java/io/IOException
    //   341	345	430	java/io/IOException
    //   350	355	434	java/io/IOException
    //   360	365	438	java/io/IOException
    //   381	386	442	java/io/IOException
    //   391	396	447	java/io/IOException
    //   400	404	452	java/io/IOException
    //   47	74	456	finally
    //   74	94	474	finally
    //   94	162	491	finally
    //   170	181	491	finally
    //   188	194	491	finally
    //   47	74	512	java/io/IOException
    //   74	94	525	java/io/IOException
    //   94	162	537	java/io/IOException
    //   170	181	537	java/io/IOException
    //   188	194	537	java/io/IOException
    //   47	74	549	java/net/UnknownHostException
    //   74	94	554	java/net/UnknownHostException
    //   94	162	562	java/net/UnknownHostException
    //   170	181	562	java/net/UnknownHostException
    //   188	194	562	java/net/UnknownHostException
  }
}

/* Location:
 * Qualified Name:     com.threatmetrix.TrustDefenderMobile.PutXML
 * Java Class Version: 6 (50.0)
 * JD-Core Version:    0.7.1
 */