package com.mobileapptracker;

import android.content.Context;
import android.content.SharedPreferences;
import android.content.SharedPreferences.Editor;
import java.util.concurrent.Semaphore;
import org.json.JSONObject;

public class MATEventQueue
{
  private static long retryTimeout = 0L;
  private SharedPreferences eventQueue;
  private Semaphore queueAvailable;
  private MobileAppTracker tune;
  
  public MATEventQueue(Context paramContext, MobileAppTracker paramMobileAppTracker)
  {
    eventQueue = paramContext.getSharedPreferences("mat_queue", 0);
    queueAvailable = new Semaphore(1, true);
    tune = paramMobileAppTracker;
  }
  
  protected String getKeyFromQueue(String paramString)
  {
    try
    {
      paramString = eventQueue.getString(paramString, null);
      return paramString;
    }
    finally
    {
      paramString = finally;
      throw paramString;
    }
  }
  
  protected int getQueueSize()
  {
    try
    {
      int i = eventQueue.getInt("queuesize", 0);
      return i;
    }
    finally
    {
      localObject = finally;
      throw ((Throwable)localObject);
    }
  }
  
  protected void removeKeyFromQueue(String paramString)
  {
    try
    {
      setQueueSize(getQueueSize() - 1);
      SharedPreferences.Editor localEditor = eventQueue.edit();
      localEditor.remove(paramString);
      localEditor.commit();
      return;
    }
    finally
    {
      paramString = finally;
      throw paramString;
    }
  }
  
  protected void setQueueItemForKey(JSONObject paramJSONObject, String paramString)
  {
    try
    {
      SharedPreferences.Editor localEditor = eventQueue.edit();
      localEditor.putString(paramString, paramJSONObject.toString());
      localEditor.commit();
      return;
    }
    finally
    {
      paramJSONObject = finally;
      throw paramJSONObject;
    }
  }
  
  protected void setQueueSize(int paramInt)
  {
    try
    {
      SharedPreferences.Editor localEditor = eventQueue.edit();
      int i = paramInt;
      if (paramInt < 0) {
        i = 0;
      }
      localEditor.putInt("queuesize", i);
      localEditor.commit();
      return;
    }
    finally {}
  }
  
  protected class Add
    implements Runnable
  {
    private String data = null;
    private boolean firstSession = false;
    private String link = null;
    private JSONObject postBody = null;
    
    protected Add(String paramString1, String paramString2, JSONObject paramJSONObject, boolean paramBoolean)
    {
      link = paramString1;
      data = paramString2;
      postBody = paramJSONObject;
      firstSession = paramBoolean;
    }
    
    /* Error */
    public void run()
    {
      // Byte code:
      //   0: aload_0
      //   1: getfield 22	com/mobileapptracker/MATEventQueue$Add:this$0	Lcom/mobileapptracker/MATEventQueue;
      //   4: invokestatic 43	com/mobileapptracker/MATEventQueue:access$000	(Lcom/mobileapptracker/MATEventQueue;)Ljava/util/concurrent/Semaphore;
      //   7: invokevirtual 48	java/util/concurrent/Semaphore:acquire	()V
      //   10: new 50	org/json/JSONObject
      //   13: dup
      //   14: invokespecial 51	org/json/JSONObject:<init>	()V
      //   17: astore_2
      //   18: aload_2
      //   19: ldc 52
      //   21: aload_0
      //   22: getfield 27	com/mobileapptracker/MATEventQueue$Add:link	Ljava/lang/String;
      //   25: invokevirtual 56	org/json/JSONObject:put	(Ljava/lang/String;Ljava/lang/Object;)Lorg/json/JSONObject;
      //   28: pop
      //   29: aload_2
      //   30: ldc 57
      //   32: aload_0
      //   33: getfield 29	com/mobileapptracker/MATEventQueue$Add:data	Ljava/lang/String;
      //   36: invokevirtual 56	org/json/JSONObject:put	(Ljava/lang/String;Ljava/lang/Object;)Lorg/json/JSONObject;
      //   39: pop
      //   40: aload_2
      //   41: ldc 59
      //   43: aload_0
      //   44: getfield 31	com/mobileapptracker/MATEventQueue$Add:postBody	Lorg/json/JSONObject;
      //   47: invokevirtual 56	org/json/JSONObject:put	(Ljava/lang/String;Ljava/lang/Object;)Lorg/json/JSONObject;
      //   50: pop
      //   51: aload_2
      //   52: ldc 61
      //   54: aload_0
      //   55: getfield 33	com/mobileapptracker/MATEventQueue$Add:firstSession	Z
      //   58: invokevirtual 64	org/json/JSONObject:put	(Ljava/lang/String;Z)Lorg/json/JSONObject;
      //   61: pop
      //   62: aload_0
      //   63: getfield 22	com/mobileapptracker/MATEventQueue$Add:this$0	Lcom/mobileapptracker/MATEventQueue;
      //   66: invokevirtual 68	com/mobileapptracker/MATEventQueue:getQueueSize	()I
      //   69: iconst_1
      //   70: iadd
      //   71: istore_1
      //   72: aload_0
      //   73: getfield 22	com/mobileapptracker/MATEventQueue$Add:this$0	Lcom/mobileapptracker/MATEventQueue;
      //   76: iload_1
      //   77: invokevirtual 72	com/mobileapptracker/MATEventQueue:setQueueSize	(I)V
      //   80: iload_1
      //   81: invokestatic 78	java/lang/Integer:toString	(I)Ljava/lang/String;
      //   84: astore_3
      //   85: aload_0
      //   86: getfield 22	com/mobileapptracker/MATEventQueue$Add:this$0	Lcom/mobileapptracker/MATEventQueue;
      //   89: aload_2
      //   90: aload_3
      //   91: invokevirtual 82	com/mobileapptracker/MATEventQueue:setQueueItemForKey	(Lorg/json/JSONObject;Ljava/lang/String;)V
      //   94: aload_0
      //   95: getfield 22	com/mobileapptracker/MATEventQueue$Add:this$0	Lcom/mobileapptracker/MATEventQueue;
      //   98: invokestatic 43	com/mobileapptracker/MATEventQueue:access$000	(Lcom/mobileapptracker/MATEventQueue;)Ljava/util/concurrent/Semaphore;
      //   101: invokevirtual 85	java/util/concurrent/Semaphore:release	()V
      //   104: return
      //   105: astore_2
      //   106: ldc 87
      //   108: ldc 89
      //   110: invokestatic 95	android/util/Log:w	(Ljava/lang/String;Ljava/lang/String;)I
      //   113: pop
      //   114: aload_2
      //   115: invokevirtual 98	org/json/JSONException:printStackTrace	()V
      //   118: aload_0
      //   119: getfield 22	com/mobileapptracker/MATEventQueue$Add:this$0	Lcom/mobileapptracker/MATEventQueue;
      //   122: invokestatic 43	com/mobileapptracker/MATEventQueue:access$000	(Lcom/mobileapptracker/MATEventQueue;)Ljava/util/concurrent/Semaphore;
      //   125: invokevirtual 85	java/util/concurrent/Semaphore:release	()V
      //   128: return
      //   129: astore_2
      //   130: ldc 87
      //   132: ldc 100
      //   134: invokestatic 95	android/util/Log:w	(Ljava/lang/String;Ljava/lang/String;)I
      //   137: pop
      //   138: aload_2
      //   139: invokevirtual 101	java/lang/InterruptedException:printStackTrace	()V
      //   142: aload_0
      //   143: getfield 22	com/mobileapptracker/MATEventQueue$Add:this$0	Lcom/mobileapptracker/MATEventQueue;
      //   146: invokestatic 43	com/mobileapptracker/MATEventQueue:access$000	(Lcom/mobileapptracker/MATEventQueue;)Ljava/util/concurrent/Semaphore;
      //   149: invokevirtual 85	java/util/concurrent/Semaphore:release	()V
      //   152: return
      //   153: astore_2
      //   154: aload_0
      //   155: getfield 22	com/mobileapptracker/MATEventQueue$Add:this$0	Lcom/mobileapptracker/MATEventQueue;
      //   158: invokestatic 43	com/mobileapptracker/MATEventQueue:access$000	(Lcom/mobileapptracker/MATEventQueue;)Ljava/util/concurrent/Semaphore;
      //   161: invokevirtual 85	java/util/concurrent/Semaphore:release	()V
      //   164: aload_2
      //   165: athrow
      // Local variable table:
      //   start	length	slot	name	signature
      //   0	166	0	this	Add
      //   71	10	1	i	int
      //   17	73	2	localJSONObject	JSONObject
      //   105	10	2	localJSONException	org.json.JSONException
      //   129	10	2	localInterruptedException	InterruptedException
      //   153	12	2	localObject	Object
      //   84	7	3	str	String
      // Exception table:
      //   from	to	target	type
      //   18	62	105	org/json/JSONException
      //   0	18	129	java/lang/InterruptedException
      //   18	62	129	java/lang/InterruptedException
      //   62	94	129	java/lang/InterruptedException
      //   106	118	129	java/lang/InterruptedException
      //   0	18	153	finally
      //   18	62	153	finally
      //   62	94	153	finally
      //   106	118	153	finally
      //   130	142	153	finally
    }
  }
  
  protected class Dump
    implements Runnable
  {
    protected Dump() {}
    
    /* Error */
    public void run()
    {
      // Byte code:
      //   0: aload_0
      //   1: getfield 15	com/mobileapptracker/MATEventQueue$Dump:this$0	Lcom/mobileapptracker/MATEventQueue;
      //   4: invokevirtual 32	com/mobileapptracker/MATEventQueue:getQueueSize	()I
      //   7: istore 7
      //   9: iload 7
      //   11: ifne +4 -> 15
      //   14: return
      //   15: aload_0
      //   16: getfield 15	com/mobileapptracker/MATEventQueue$Dump:this$0	Lcom/mobileapptracker/MATEventQueue;
      //   19: invokestatic 36	com/mobileapptracker/MATEventQueue:access$000	(Lcom/mobileapptracker/MATEventQueue;)Ljava/util/concurrent/Semaphore;
      //   22: invokevirtual 41	java/util/concurrent/Semaphore:acquire	()V
      //   25: iconst_1
      //   26: istore_3
      //   27: iload 7
      //   29: bipush 50
      //   31: if_icmple +11 -> 42
      //   34: iload 7
      //   36: bipush 50
      //   38: isub
      //   39: iconst_1
      //   40: iadd
      //   41: istore_3
      //   42: iload_3
      //   43: iload 7
      //   45: if_icmpgt +562 -> 607
      //   48: iload_3
      //   49: invokestatic 47	java/lang/Integer:toString	(I)Ljava/lang/String;
      //   52: astore 12
      //   54: aload_0
      //   55: getfield 15	com/mobileapptracker/MATEventQueue$Dump:this$0	Lcom/mobileapptracker/MATEventQueue;
      //   58: aload 12
      //   60: invokevirtual 51	com/mobileapptracker/MATEventQueue:getKeyFromQueue	(Ljava/lang/String;)Ljava/lang/String;
      //   63: astore 13
      //   65: aload 13
      //   67: ifnull +520 -> 587
      //   70: new 53	org/json/JSONObject
      //   73: dup
      //   74: aload 13
      //   76: invokespecial 56	org/json/JSONObject:<init>	(Ljava/lang/String;)V
      //   79: astore 17
      //   81: aload 17
      //   83: ldc 58
      //   85: invokevirtual 61	org/json/JSONObject:getString	(Ljava/lang/String;)Ljava/lang/String;
      //   88: astore 14
      //   90: aload 17
      //   92: ldc 63
      //   94: invokevirtual 61	org/json/JSONObject:getString	(Ljava/lang/String;)Ljava/lang/String;
      //   97: astore 15
      //   99: aload 17
      //   101: ldc 65
      //   103: invokevirtual 69	org/json/JSONObject:getJSONObject	(Ljava/lang/String;)Lorg/json/JSONObject;
      //   106: astore 16
      //   108: aload 17
      //   110: ldc 71
      //   112: invokevirtual 75	org/json/JSONObject:getBoolean	(Ljava/lang/String;)Z
      //   115: istore 9
      //   117: iload 9
      //   119: ifeq +37 -> 156
      //   122: aload_0
      //   123: getfield 15	com/mobileapptracker/MATEventQueue$Dump:this$0	Lcom/mobileapptracker/MATEventQueue;
      //   126: invokestatic 79	com/mobileapptracker/MATEventQueue:access$100	(Lcom/mobileapptracker/MATEventQueue;)Lcom/mobileapptracker/MobileAppTracker;
      //   129: getfield 85	com/mobileapptracker/MobileAppTracker:pool	Ljava/util/concurrent/ExecutorService;
      //   132: astore 17
      //   134: aload 17
      //   136: monitorenter
      //   137: aload_0
      //   138: getfield 15	com/mobileapptracker/MATEventQueue$Dump:this$0	Lcom/mobileapptracker/MATEventQueue;
      //   141: invokestatic 79	com/mobileapptracker/MATEventQueue:access$100	(Lcom/mobileapptracker/MATEventQueue;)Lcom/mobileapptracker/MobileAppTracker;
      //   144: getfield 85	com/mobileapptracker/MobileAppTracker:pool	Ljava/util/concurrent/ExecutorService;
      //   147: ldc2_w 86
      //   150: invokevirtual 91	java/lang/Object:wait	(J)V
      //   153: aload 17
      //   155: monitorexit
      //   156: aload_0
      //   157: getfield 15	com/mobileapptracker/MATEventQueue$Dump:this$0	Lcom/mobileapptracker/MATEventQueue;
      //   160: invokestatic 79	com/mobileapptracker/MATEventQueue:access$100	(Lcom/mobileapptracker/MATEventQueue;)Lcom/mobileapptracker/MobileAppTracker;
      //   163: ifnull +404 -> 567
      //   166: aload_0
      //   167: getfield 15	com/mobileapptracker/MATEventQueue$Dump:this$0	Lcom/mobileapptracker/MATEventQueue;
      //   170: invokestatic 79	com/mobileapptracker/MATEventQueue:access$100	(Lcom/mobileapptracker/MATEventQueue;)Lcom/mobileapptracker/MobileAppTracker;
      //   173: aload 14
      //   175: aload 15
      //   177: aload 16
      //   179: invokevirtual 95	com/mobileapptracker/MobileAppTracker:makeRequest	(Ljava/lang/String;Ljava/lang/String;Lorg/json/JSONObject;)Z
      //   182: ifeq +73 -> 255
      //   185: aload_0
      //   186: getfield 15	com/mobileapptracker/MATEventQueue$Dump:this$0	Lcom/mobileapptracker/MATEventQueue;
      //   189: aload 12
      //   191: invokevirtual 98	com/mobileapptracker/MATEventQueue:removeKeyFromQueue	(Ljava/lang/String;)V
      //   194: lconst_0
      //   195: invokestatic 102	com/mobileapptracker/MATEventQueue:access$202	(J)J
      //   198: pop2
      //   199: goto +419 -> 618
      //   202: astore 13
      //   204: aload 13
      //   206: invokevirtual 105	org/json/JSONException:printStackTrace	()V
      //   209: aload_0
      //   210: getfield 15	com/mobileapptracker/MATEventQueue$Dump:this$0	Lcom/mobileapptracker/MATEventQueue;
      //   213: aload 12
      //   215: invokevirtual 98	com/mobileapptracker/MATEventQueue:removeKeyFromQueue	(Ljava/lang/String;)V
      //   218: aload_0
      //   219: getfield 15	com/mobileapptracker/MATEventQueue$Dump:this$0	Lcom/mobileapptracker/MATEventQueue;
      //   222: invokestatic 36	com/mobileapptracker/MATEventQueue:access$000	(Lcom/mobileapptracker/MATEventQueue;)Ljava/util/concurrent/Semaphore;
      //   225: invokevirtual 108	java/util/concurrent/Semaphore:release	()V
      //   228: return
      //   229: astore 12
      //   231: aload 17
      //   233: monitorexit
      //   234: aload 12
      //   236: athrow
      //   237: astore 12
      //   239: aload 12
      //   241: invokevirtual 109	java/lang/InterruptedException:printStackTrace	()V
      //   244: aload_0
      //   245: getfield 15	com/mobileapptracker/MATEventQueue$Dump:this$0	Lcom/mobileapptracker/MATEventQueue;
      //   248: invokestatic 36	com/mobileapptracker/MATEventQueue:access$000	(Lcom/mobileapptracker/MATEventQueue;)Ljava/util/concurrent/Semaphore;
      //   251: invokevirtual 108	java/util/concurrent/Semaphore:release	()V
      //   254: return
      //   255: iload_3
      //   256: iconst_1
      //   257: isub
      //   258: istore 5
      //   260: aload 14
      //   262: ldc 111
      //   264: invokevirtual 117	java/lang/String:indexOf	(Ljava/lang/String;)I
      //   267: istore_3
      //   268: iload_3
      //   269: ifle +117 -> 386
      //   272: iconst_m1
      //   273: istore 4
      //   275: ldc 111
      //   277: invokevirtual 120	java/lang/String:length	()I
      //   280: istore 6
      //   282: iload_3
      //   283: iload 6
      //   285: iadd
      //   286: istore 8
      //   288: iload 8
      //   290: iconst_1
      //   291: iadd
      //   292: istore_3
      //   293: aload 14
      //   295: iload 8
      //   297: iload_3
      //   298: invokevirtual 124	java/lang/String:substring	(II)Ljava/lang/String;
      //   301: astore 15
      //   303: aload 15
      //   305: invokestatic 127	java/lang/Integer:parseInt	(Ljava/lang/String;)I
      //   308: istore 6
      //   310: iload 6
      //   312: istore 4
      //   314: iload_3
      //   315: iconst_1
      //   316: iadd
      //   317: istore_3
      //   318: goto -25 -> 293
      //   321: astore 15
      //   323: aload 14
      //   325: ldc -127
      //   327: new 131	java/lang/StringBuilder
      //   330: dup
      //   331: invokespecial 132	java/lang/StringBuilder:<init>	()V
      //   334: ldc 111
      //   336: invokevirtual 136	java/lang/StringBuilder:append	(Ljava/lang/String;)Ljava/lang/StringBuilder;
      //   339: iload 4
      //   341: iconst_1
      //   342: iadd
      //   343: invokevirtual 139	java/lang/StringBuilder:append	(I)Ljava/lang/StringBuilder;
      //   346: invokevirtual 142	java/lang/StringBuilder:toString	()Ljava/lang/String;
      //   349: invokevirtual 146	java/lang/String:replaceFirst	(Ljava/lang/String;Ljava/lang/String;)Ljava/lang/String;
      //   352: astore 14
      //   354: new 53	org/json/JSONObject
      //   357: dup
      //   358: aload 13
      //   360: invokespecial 56	org/json/JSONObject:<init>	(Ljava/lang/String;)V
      //   363: astore 13
      //   365: aload 13
      //   367: ldc 58
      //   369: aload 14
      //   371: invokevirtual 150	org/json/JSONObject:put	(Ljava/lang/String;Ljava/lang/Object;)Lorg/json/JSONObject;
      //   374: pop
      //   375: aload_0
      //   376: getfield 15	com/mobileapptracker/MATEventQueue$Dump:this$0	Lcom/mobileapptracker/MATEventQueue;
      //   379: aload 13
      //   381: aload 12
      //   383: invokevirtual 154	com/mobileapptracker/MATEventQueue:setQueueItemForKey	(Lorg/json/JSONObject;Ljava/lang/String;)V
      //   386: invokestatic 158	com/mobileapptracker/MATEventQueue:access$200	()J
      //   389: lconst_0
      //   390: lcmp
      //   391: ifne +86 -> 477
      //   394: ldc2_w 159
      //   397: invokestatic 102	com/mobileapptracker/MATEventQueue:access$202	(J)J
      //   400: pop2
      //   401: invokestatic 166	java/lang/Math:random	()D
      //   404: dstore_1
      //   405: invokestatic 158	com/mobileapptracker/MATEventQueue:access$200	()J
      //   408: lstore 10
      //   410: dconst_1
      //   411: ldc2_w 167
      //   414: dload_1
      //   415: dmul
      //   416: dadd
      //   417: lload 10
      //   419: l2d
      //   420: dmul
      //   421: ldc2_w 169
      //   424: dmul
      //   425: d2l
      //   426: lstore 10
      //   428: lload 10
      //   430: invokestatic 175	java/lang/Thread:sleep	(J)V
      //   433: iload 5
      //   435: istore_3
      //   436: goto +182 -> 618
      //   439: astore 12
      //   441: iload 5
      //   443: istore_3
      //   444: goto +174 -> 618
      //   447: astore 15
      //   449: goto -126 -> 323
      //   452: astore 12
      //   454: aload 12
      //   456: invokevirtual 105	org/json/JSONException:printStackTrace	()V
      //   459: goto -73 -> 386
      //   462: astore 12
      //   464: aload_0
      //   465: getfield 15	com/mobileapptracker/MATEventQueue$Dump:this$0	Lcom/mobileapptracker/MATEventQueue;
      //   468: invokestatic 36	com/mobileapptracker/MATEventQueue:access$000	(Lcom/mobileapptracker/MATEventQueue;)Ljava/util/concurrent/Semaphore;
      //   471: invokevirtual 108	java/util/concurrent/Semaphore:release	()V
      //   474: aload 12
      //   476: athrow
      //   477: invokestatic 158	com/mobileapptracker/MATEventQueue:access$200	()J
      //   480: ldc2_w 159
      //   483: lcmp
      //   484: ifgt +13 -> 497
      //   487: ldc2_w 176
      //   490: invokestatic 102	com/mobileapptracker/MATEventQueue:access$202	(J)J
      //   493: pop2
      //   494: goto -93 -> 401
      //   497: invokestatic 158	com/mobileapptracker/MATEventQueue:access$200	()J
      //   500: ldc2_w 176
      //   503: lcmp
      //   504: ifgt +13 -> 517
      //   507: ldc2_w 178
      //   510: invokestatic 102	com/mobileapptracker/MATEventQueue:access$202	(J)J
      //   513: pop2
      //   514: goto -113 -> 401
      //   517: invokestatic 158	com/mobileapptracker/MATEventQueue:access$200	()J
      //   520: ldc2_w 178
      //   523: lcmp
      //   524: ifgt +13 -> 537
      //   527: ldc2_w 180
      //   530: invokestatic 102	com/mobileapptracker/MATEventQueue:access$202	(J)J
      //   533: pop2
      //   534: goto -133 -> 401
      //   537: invokestatic 158	com/mobileapptracker/MATEventQueue:access$200	()J
      //   540: ldc2_w 180
      //   543: lcmp
      //   544: ifgt +13 -> 557
      //   547: ldc2_w 182
      //   550: invokestatic 102	com/mobileapptracker/MATEventQueue:access$202	(J)J
      //   553: pop2
      //   554: goto -153 -> 401
      //   557: ldc2_w 184
      //   560: invokestatic 102	com/mobileapptracker/MATEventQueue:access$202	(J)J
      //   563: pop2
      //   564: goto -163 -> 401
      //   567: ldc -69
      //   569: ldc -67
      //   571: invokestatic 195	android/util/Log:d	(Ljava/lang/String;Ljava/lang/String;)I
      //   574: pop
      //   575: aload_0
      //   576: getfield 15	com/mobileapptracker/MATEventQueue$Dump:this$0	Lcom/mobileapptracker/MATEventQueue;
      //   579: aload 12
      //   581: invokevirtual 98	com/mobileapptracker/MATEventQueue:removeKeyFromQueue	(Ljava/lang/String;)V
      //   584: goto +34 -> 618
      //   587: ldc -69
      //   589: ldc -59
      //   591: invokestatic 195	android/util/Log:d	(Ljava/lang/String;Ljava/lang/String;)I
      //   594: pop
      //   595: aload_0
      //   596: getfield 15	com/mobileapptracker/MATEventQueue$Dump:this$0	Lcom/mobileapptracker/MATEventQueue;
      //   599: aload 12
      //   601: invokevirtual 98	com/mobileapptracker/MATEventQueue:removeKeyFromQueue	(Ljava/lang/String;)V
      //   604: goto +14 -> 618
      //   607: aload_0
      //   608: getfield 15	com/mobileapptracker/MATEventQueue$Dump:this$0	Lcom/mobileapptracker/MATEventQueue;
      //   611: invokestatic 36	com/mobileapptracker/MATEventQueue:access$000	(Lcom/mobileapptracker/MATEventQueue;)Ljava/util/concurrent/Semaphore;
      //   614: invokevirtual 108	java/util/concurrent/Semaphore:release	()V
      //   617: return
      //   618: iload_3
      //   619: iconst_1
      //   620: iadd
      //   621: istore_3
      //   622: goto -580 -> 42
      // Local variable table:
      //   start	length	slot	name	signature
      //   0	625	0	this	Dump
      //   404	11	1	d	double
      //   26	596	3	i	int
      //   273	70	4	j	int
      //   258	184	5	k	int
      //   280	31	6	m	int
      //   7	39	7	n	int
      //   286	10	8	i1	int
      //   115	3	9	bool	boolean
      //   408	21	10	l	long
      //   52	162	12	str1	String
      //   229	6	12	localObject1	Object
      //   237	145	12	localInterruptedException1	InterruptedException
      //   439	1	12	localInterruptedException2	InterruptedException
      //   452	3	12	localJSONException1	org.json.JSONException
      //   462	138	12	str2	String
      //   63	12	13	str3	String
      //   202	157	13	localJSONException2	org.json.JSONException
      //   363	17	13	localJSONObject1	JSONObject
      //   88	282	14	str4	String
      //   97	207	15	str5	String
      //   321	1	15	localStringIndexOutOfBoundsException	StringIndexOutOfBoundsException
      //   447	1	15	localNumberFormatException	NumberFormatException
      //   106	72	16	localJSONObject2	JSONObject
      //   79	153	17	localObject2	Object
      // Exception table:
      //   from	to	target	type
      //   70	117	202	org/json/JSONException
      //   137	156	229	finally
      //   231	234	229	finally
      //   15	25	237	java/lang/InterruptedException
      //   48	65	237	java/lang/InterruptedException
      //   70	117	237	java/lang/InterruptedException
      //   122	137	237	java/lang/InterruptedException
      //   156	199	237	java/lang/InterruptedException
      //   204	218	237	java/lang/InterruptedException
      //   234	237	237	java/lang/InterruptedException
      //   260	268	237	java/lang/InterruptedException
      //   275	282	237	java/lang/InterruptedException
      //   293	303	237	java/lang/InterruptedException
      //   303	310	237	java/lang/InterruptedException
      //   323	354	237	java/lang/InterruptedException
      //   354	386	237	java/lang/InterruptedException
      //   386	401	237	java/lang/InterruptedException
      //   401	410	237	java/lang/InterruptedException
      //   454	459	237	java/lang/InterruptedException
      //   477	494	237	java/lang/InterruptedException
      //   497	514	237	java/lang/InterruptedException
      //   517	534	237	java/lang/InterruptedException
      //   537	554	237	java/lang/InterruptedException
      //   557	564	237	java/lang/InterruptedException
      //   567	584	237	java/lang/InterruptedException
      //   587	604	237	java/lang/InterruptedException
      //   293	303	321	java/lang/StringIndexOutOfBoundsException
      //   428	433	439	java/lang/InterruptedException
      //   303	310	447	java/lang/NumberFormatException
      //   354	386	452	org/json/JSONException
      //   15	25	462	finally
      //   48	65	462	finally
      //   70	117	462	finally
      //   122	137	462	finally
      //   156	199	462	finally
      //   204	218	462	finally
      //   234	237	462	finally
      //   239	244	462	finally
      //   260	268	462	finally
      //   275	282	462	finally
      //   293	303	462	finally
      //   303	310	462	finally
      //   323	354	462	finally
      //   354	386	462	finally
      //   386	401	462	finally
      //   401	410	462	finally
      //   428	433	462	finally
      //   454	459	462	finally
      //   477	494	462	finally
      //   497	514	462	finally
      //   517	534	462	finally
      //   537	554	462	finally
      //   557	564	462	finally
      //   567	584	462	finally
      //   587	604	462	finally
    }
  }
}

/* Location:
 * Qualified Name:     com.mobileapptracker.MATEventQueue
 * Java Class Version: 6 (50.0)
 * JD-Core Version:    0.7.1
 */