package com.google.android.gms.maps;

import android.graphics.Bitmap;
import android.location.Location;
import android.os.RemoteException;
import android.view.View;
import com.google.android.gms.common.internal.zzab;
import com.google.android.gms.dynamic.zze;
import com.google.android.gms.maps.internal.IGoogleMapDelegate;
import com.google.android.gms.maps.internal.ILocationSourceDelegate.zza;
import com.google.android.gms.maps.internal.zzac.zza;
import com.google.android.gms.maps.internal.zzb.zza;
import com.google.android.gms.maps.internal.zzd.zza;
import com.google.android.gms.maps.internal.zze.zza;
import com.google.android.gms.maps.internal.zzf.zza;
import com.google.android.gms.maps.internal.zzg.zza;
import com.google.android.gms.maps.internal.zzh.zza;
import com.google.android.gms.maps.internal.zzi.zza;
import com.google.android.gms.maps.internal.zzj.zza;
import com.google.android.gms.maps.internal.zzk.zza;
import com.google.android.gms.maps.internal.zzl;
import com.google.android.gms.maps.internal.zzm.zza;
import com.google.android.gms.maps.internal.zzn.zza;
import com.google.android.gms.maps.internal.zzo.zza;
import com.google.android.gms.maps.internal.zzq.zza;
import com.google.android.gms.maps.internal.zzr.zza;
import com.google.android.gms.maps.internal.zzs.zza;
import com.google.android.gms.maps.internal.zzt.zza;
import com.google.android.gms.maps.internal.zzv.zza;
import com.google.android.gms.maps.internal.zzw.zza;
import com.google.android.gms.maps.model.CameraPosition;
import com.google.android.gms.maps.model.Circle;
import com.google.android.gms.maps.model.CircleOptions;
import com.google.android.gms.maps.model.GroundOverlay;
import com.google.android.gms.maps.model.IndoorBuilding;
import com.google.android.gms.maps.model.LatLng;
import com.google.android.gms.maps.model.Marker;
import com.google.android.gms.maps.model.MarkerOptions;
import com.google.android.gms.maps.model.Polygon;
import com.google.android.gms.maps.model.PolygonOptions;
import com.google.android.gms.maps.model.Polyline;
import com.google.android.gms.maps.model.PolylineOptions;
import com.google.android.gms.maps.model.RuntimeRemoteException;
import com.google.android.gms.maps.model.TileOverlay;
import com.google.android.gms.maps.model.TileOverlayOptions;
import com.google.android.gms.maps.model.internal.IPolylineDelegate;
import com.google.android.gms.maps.model.internal.zzb;
import com.google.android.gms.maps.model.internal.zzc;
import com.google.android.gms.maps.model.internal.zzf;
import com.google.android.gms.maps.model.internal.zzg;

public final class GoogleMap
{
  private final IGoogleMapDelegate agw;
  private UiSettings agx;
  
  protected GoogleMap(IGoogleMapDelegate paramIGoogleMapDelegate)
  {
    agw = ((IGoogleMapDelegate)zzab.zzaa(paramIGoogleMapDelegate));
  }
  
  public final Circle addCircle(CircleOptions paramCircleOptions)
  {
    try
    {
      paramCircleOptions = new Circle(agw.addCircle(paramCircleOptions));
      return paramCircleOptions;
    }
    catch (RemoteException paramCircleOptions)
    {
      throw new RuntimeRemoteException(paramCircleOptions);
    }
  }
  
  public final Marker addMarker(MarkerOptions paramMarkerOptions)
  {
    try
    {
      paramMarkerOptions = agw.addMarker(paramMarkerOptions);
      if (paramMarkerOptions != null)
      {
        paramMarkerOptions = new Marker(paramMarkerOptions);
        return paramMarkerOptions;
      }
      return null;
    }
    catch (RemoteException paramMarkerOptions)
    {
      throw new RuntimeRemoteException(paramMarkerOptions);
    }
  }
  
  public final Polygon addPolygon(PolygonOptions paramPolygonOptions)
  {
    try
    {
      paramPolygonOptions = new Polygon(agw.addPolygon(paramPolygonOptions));
      return paramPolygonOptions;
    }
    catch (RemoteException paramPolygonOptions)
    {
      throw new RuntimeRemoteException(paramPolygonOptions);
    }
  }
  
  public final Polyline addPolyline(PolylineOptions paramPolylineOptions)
  {
    try
    {
      paramPolylineOptions = new Polyline(agw.addPolyline(paramPolylineOptions));
      return paramPolylineOptions;
    }
    catch (RemoteException paramPolylineOptions)
    {
      throw new RuntimeRemoteException(paramPolylineOptions);
    }
  }
  
  public final TileOverlay addTileOverlay(TileOverlayOptions paramTileOverlayOptions)
  {
    try
    {
      paramTileOverlayOptions = agw.addTileOverlay(paramTileOverlayOptions);
      if (paramTileOverlayOptions != null)
      {
        paramTileOverlayOptions = new TileOverlay(paramTileOverlayOptions);
        return paramTileOverlayOptions;
      }
      return null;
    }
    catch (RemoteException paramTileOverlayOptions)
    {
      throw new RuntimeRemoteException(paramTileOverlayOptions);
    }
  }
  
  /* Error */
  public final void animateCamera(CameraUpdate paramCameraUpdate, int paramInt, CancelableCallback paramCancelableCallback)
  {
    // Byte code:
    //   0: aload_0
    //   1: getfield 123	com/google/android/gms/maps/GoogleMap:agw	Lcom/google/android/gms/maps/internal/IGoogleMapDelegate;
    //   4: astore 4
    //   6: aload_1
    //   7: invokevirtual 189	com/google/android/gms/maps/CameraUpdate:zzbpg	()Lcom/google/android/gms/dynamic/zzd;
    //   10: astore 5
    //   12: aload_3
    //   13: ifnonnull +17 -> 30
    //   16: aconst_null
    //   17: astore_1
    //   18: aload 4
    //   20: aload 5
    //   22: iload_2
    //   23: aload_1
    //   24: invokeinterface 193 4 0
    //   29: return
    //   30: new 103	com/google/android/gms/maps/GoogleMap$zza
    //   33: dup
    //   34: aload_3
    //   35: invokespecial 196	com/google/android/gms/maps/GoogleMap$zza:<init>	(Lcom/google/android/gms/maps/GoogleMap$CancelableCallback;)V
    //   38: astore_1
    //   39: goto -21 -> 18
    //   42: astore_1
    //   43: new 138	com/google/android/gms/maps/model/RuntimeRemoteException
    //   46: dup
    //   47: aload_1
    //   48: invokespecial 141	com/google/android/gms/maps/model/RuntimeRemoteException:<init>	(Landroid/os/RemoteException;)V
    //   51: athrow
    // Local variable table:
    //   start	length	slot	name	signature
    //   0	52	0	this	GoogleMap
    //   0	52	1	paramCameraUpdate	CameraUpdate
    //   0	52	2	paramInt	int
    //   0	52	3	paramCancelableCallback	CancelableCallback
    //   4	15	4	localIGoogleMapDelegate	IGoogleMapDelegate
    //   10	11	5	localzzd	com.google.android.gms.dynamic.zzd
    // Exception table:
    //   from	to	target	type
    //   0	12	42	android/os/RemoteException
    //   18	29	42	android/os/RemoteException
    //   30	39	42	android/os/RemoteException
  }
  
  public final void clear()
  {
    try
    {
      agw.clear();
      return;
    }
    catch (RemoteException localRemoteException)
    {
      throw new RuntimeRemoteException(localRemoteException);
    }
  }
  
  public final CameraPosition getCameraPosition()
  {
    try
    {
      CameraPosition localCameraPosition = agw.getCameraPosition();
      return localCameraPosition;
    }
    catch (RemoteException localRemoteException)
    {
      throw new RuntimeRemoteException(localRemoteException);
    }
  }
  
  public final Projection getProjection()
  {
    try
    {
      Projection localProjection = new Projection(agw.getProjection());
      return localProjection;
    }
    catch (RemoteException localRemoteException)
    {
      throw new RuntimeRemoteException(localRemoteException);
    }
  }
  
  public final UiSettings getUiSettings()
  {
    try
    {
      if (agx == null) {
        agx = new UiSettings(agw.getUiSettings());
      }
      UiSettings localUiSettings = agx;
      return localUiSettings;
    }
    catch (RemoteException localRemoteException)
    {
      throw new RuntimeRemoteException(localRemoteException);
    }
  }
  
  public final void moveCamera(CameraUpdate paramCameraUpdate)
  {
    try
    {
      agw.moveCamera(paramCameraUpdate.zzbpg());
      return;
    }
    catch (RemoteException paramCameraUpdate)
    {
      throw new RuntimeRemoteException(paramCameraUpdate);
    }
  }
  
  public final void setInfoWindowAdapter(final InfoWindowAdapter paramInfoWindowAdapter)
  {
    if (paramInfoWindowAdapter == null) {}
    try
    {
      agw.setInfoWindowAdapter(null);
      return;
    }
    catch (RemoteException paramInfoWindowAdapter)
    {
      throw new RuntimeRemoteException(paramInfoWindowAdapter);
    }
    agw.setInfoWindowAdapter(new zzd.zza()
    {
      public com.google.android.gms.dynamic.zzd zzb(zzf paramAnonymouszzf)
      {
        return zze.zzae(paramInfoWindowAdapter.getInfoWindow(new Marker(paramAnonymouszzf)));
      }
      
      public com.google.android.gms.dynamic.zzd zzc(zzf paramAnonymouszzf)
      {
        return zze.zzae(paramInfoWindowAdapter.getInfoContents(new Marker(paramAnonymouszzf)));
      }
    });
  }
  
  public final void setLocationSource(final LocationSource paramLocationSource)
  {
    if (paramLocationSource == null) {}
    try
    {
      agw.setLocationSource(null);
      return;
    }
    catch (RemoteException paramLocationSource)
    {
      throw new RuntimeRemoteException(paramLocationSource);
    }
    agw.setLocationSource(new ILocationSourceDelegate.zza()
    {
      public void activate(final zzl paramAnonymouszzl)
      {
        paramLocationSource.activate(new LocationSource.OnLocationChangedListener()
        {
          public void onLocationChanged(Location paramAnonymous2Location)
          {
            try
            {
              paramAnonymouszzl.zzd(paramAnonymous2Location);
              return;
            }
            catch (RemoteException paramAnonymous2Location)
            {
              throw new RuntimeRemoteException(paramAnonymous2Location);
            }
          }
        });
      }
      
      public void deactivate()
      {
        paramLocationSource.deactivate();
      }
    });
  }
  
  public final void setMyLocationEnabled(boolean paramBoolean)
  {
    try
    {
      agw.setMyLocationEnabled(paramBoolean);
      return;
    }
    catch (RemoteException localRemoteException)
    {
      throw new RuntimeRemoteException(localRemoteException);
    }
  }
  
  public final void setOnCameraChangeListener(final OnCameraChangeListener paramOnCameraChangeListener)
  {
    if (paramOnCameraChangeListener == null) {}
    try
    {
      agw.setOnCameraChangeListener(null);
      return;
    }
    catch (RemoteException paramOnCameraChangeListener)
    {
      throw new RuntimeRemoteException(paramOnCameraChangeListener);
    }
    agw.setOnCameraChangeListener(new zze.zza()
    {
      public void onCameraChange(CameraPosition paramAnonymousCameraPosition)
      {
        paramOnCameraChangeListener.onCameraChange(paramAnonymousCameraPosition);
      }
    });
  }
  
  public final void setOnInfoWindowClickListener(final OnInfoWindowClickListener paramOnInfoWindowClickListener)
  {
    if (paramOnInfoWindowClickListener == null) {}
    try
    {
      agw.setOnInfoWindowClickListener(null);
      return;
    }
    catch (RemoteException paramOnInfoWindowClickListener)
    {
      throw new RuntimeRemoteException(paramOnInfoWindowClickListener);
    }
    agw.setOnInfoWindowClickListener(new zzi.zza()
    {
      public void zzh(zzf paramAnonymouszzf)
      {
        paramOnInfoWindowClickListener.onInfoWindowClick(new Marker(paramAnonymouszzf));
      }
    });
  }
  
  public final void setOnInfoWindowCloseListener(final OnInfoWindowCloseListener paramOnInfoWindowCloseListener)
  {
    if (paramOnInfoWindowCloseListener == null) {}
    try
    {
      agw.setOnInfoWindowCloseListener(null);
      return;
    }
    catch (RemoteException paramOnInfoWindowCloseListener)
    {
      throw new RuntimeRemoteException(paramOnInfoWindowCloseListener);
    }
    agw.setOnInfoWindowCloseListener(new zzj.zza()
    {
      public void zza(zzf paramAnonymouszzf)
      {
        paramOnInfoWindowCloseListener.onInfoWindowClose(new Marker(paramAnonymouszzf));
      }
    });
  }
  
  public final void setOnMarkerClickListener(final OnMarkerClickListener paramOnMarkerClickListener)
  {
    if (paramOnMarkerClickListener == null) {}
    try
    {
      agw.setOnMarkerClickListener(null);
      return;
    }
    catch (RemoteException paramOnMarkerClickListener)
    {
      throw new RuntimeRemoteException(paramOnMarkerClickListener);
    }
    agw.setOnMarkerClickListener(new zzq.zza()
    {
      public boolean zzd(zzf paramAnonymouszzf)
      {
        return paramOnMarkerClickListener.onMarkerClick(new Marker(paramAnonymouszzf));
      }
    });
  }
  
  public final void setPadding(int paramInt1, int paramInt2, int paramInt3, int paramInt4)
  {
    try
    {
      agw.setPadding(paramInt1, paramInt2, paramInt3, paramInt4);
      return;
    }
    catch (RemoteException localRemoteException)
    {
      throw new RuntimeRemoteException(localRemoteException);
    }
  }
  
  public final void setTrafficEnabled(boolean paramBoolean)
  {
    try
    {
      agw.setTrafficEnabled(paramBoolean);
      return;
    }
    catch (RemoteException localRemoteException)
    {
      throw new RuntimeRemoteException(localRemoteException);
    }
  }
  
  public final void snapshot(SnapshotReadyCallback paramSnapshotReadyCallback)
  {
    snapshot(paramSnapshotReadyCallback, null);
  }
  
  public final void snapshot(final SnapshotReadyCallback paramSnapshotReadyCallback, Bitmap paramBitmap)
  {
    if (paramBitmap != null) {}
    for (paramBitmap = zze.zzae(paramBitmap);; paramBitmap = null)
    {
      paramBitmap = (zze)paramBitmap;
      try
      {
        agw.snapshot(new zzac.zza()
        {
          public void onSnapshotReady(Bitmap paramAnonymousBitmap)
            throws RemoteException
          {
            paramSnapshotReadyCallback.onSnapshotReady(paramAnonymousBitmap);
          }
          
          public void zzaf(com.google.android.gms.dynamic.zzd paramAnonymouszzd)
            throws RemoteException
          {
            paramSnapshotReadyCallback.onSnapshotReady((Bitmap)zze.zzad(paramAnonymouszzd));
          }
        }, paramBitmap);
        return;
      }
      catch (RemoteException paramSnapshotReadyCallback)
      {
        throw new RuntimeRemoteException(paramSnapshotReadyCallback);
      }
    }
  }
  
  public final void stopAnimation()
  {
    try
    {
      agw.stopAnimation();
      return;
    }
    catch (RemoteException localRemoteException)
    {
      throw new RuntimeRemoteException(localRemoteException);
    }
  }
  
  public static abstract interface CancelableCallback
  {
    public abstract void onCancel();
    
    public abstract void onFinish();
  }
  
  public static abstract interface InfoWindowAdapter
  {
    public abstract View getInfoContents(Marker paramMarker);
    
    public abstract View getInfoWindow(Marker paramMarker);
  }
  
  public static abstract interface OnCameraChangeListener
  {
    public abstract void onCameraChange(CameraPosition paramCameraPosition);
  }
  
  public static abstract interface OnCircleClickListener
  {
    public abstract void onCircleClick(Circle paramCircle);
  }
  
  public static abstract interface OnGroundOverlayClickListener
  {
    public abstract void onGroundOverlayClick(GroundOverlay paramGroundOverlay);
  }
  
  public static abstract interface OnIndoorStateChangeListener
  {
    public abstract void onIndoorBuildingFocused();
    
    public abstract void onIndoorLevelActivated(IndoorBuilding paramIndoorBuilding);
  }
  
  public static abstract interface OnInfoWindowClickListener
  {
    public abstract void onInfoWindowClick(Marker paramMarker);
  }
  
  public static abstract interface OnInfoWindowCloseListener
  {
    public abstract void onInfoWindowClose(Marker paramMarker);
  }
  
  public static abstract interface OnInfoWindowLongClickListener
  {
    public abstract void onInfoWindowLongClick(Marker paramMarker);
  }
  
  public static abstract interface OnMapClickListener
  {
    public abstract void onMapClick(LatLng paramLatLng);
  }
  
  public static abstract interface OnMapLoadedCallback
  {
    public abstract void onMapLoaded();
  }
  
  public static abstract interface OnMapLongClickListener
  {
    public abstract void onMapLongClick(LatLng paramLatLng);
  }
  
  public static abstract interface OnMarkerClickListener
  {
    public abstract boolean onMarkerClick(Marker paramMarker);
  }
  
  public static abstract interface OnMarkerDragListener
  {
    public abstract void onMarkerDrag(Marker paramMarker);
    
    public abstract void onMarkerDragEnd(Marker paramMarker);
    
    public abstract void onMarkerDragStart(Marker paramMarker);
  }
  
  public static abstract interface OnMyLocationButtonClickListener
  {
    public abstract boolean onMyLocationButtonClick();
  }
  
  @Deprecated
  public static abstract interface OnMyLocationChangeListener
  {
    public abstract void onMyLocationChange(Location paramLocation);
  }
  
  public static abstract interface OnPolygonClickListener
  {
    public abstract void onPolygonClick(Polygon paramPolygon);
  }
  
  public static abstract interface OnPolylineClickListener
  {
    public abstract void onPolylineClick(Polyline paramPolyline);
  }
  
  public static abstract interface SnapshotReadyCallback
  {
    public abstract void onSnapshotReady(Bitmap paramBitmap);
  }
  
  private static final class zza
    extends zzb.zza
  {
    private final GoogleMap.CancelableCallback agU;
    
    zza(GoogleMap.CancelableCallback paramCancelableCallback)
    {
      agU = paramCancelableCallback;
    }
    
    public void onCancel()
    {
      agU.onCancel();
    }
    
    public void onFinish()
    {
      agU.onFinish();
    }
  }
}

/* Location:
 * Qualified Name:     com.google.android.gms.maps.GoogleMap
 * Java Class Version: 6 (50.0)
 * JD-Core Version:    0.7.1
 */