package com.google.android.gms.maps.model.internal;

import android.os.IBinder;
import android.os.Parcel;
import android.os.RemoteException;
import com.google.android.gms.maps.model.LatLng;
import java.util.ArrayList;
import java.util.List;

class zzg$zza$zza
  implements zzg
{
  private IBinder zzahn;
  
  zzg$zza$zza(IBinder paramIBinder)
  {
    zzahn = paramIBinder;
  }
  
  public IBinder asBinder()
  {
    return zzahn;
  }
  
  public int getFillColor()
    throws RemoteException
  {
    Parcel localParcel1 = Parcel.obtain();
    Parcel localParcel2 = Parcel.obtain();
    try
    {
      localParcel1.writeInterfaceToken("com.google.android.gms.maps.model.internal.IPolygonDelegate");
      zzahn.transact(12, localParcel1, localParcel2, 0);
      localParcel2.readException();
      int i = localParcel2.readInt();
      return i;
    }
    finally
    {
      localParcel2.recycle();
      localParcel1.recycle();
    }
  }
  
  public List getHoles()
    throws RemoteException
  {
    Parcel localParcel1 = Parcel.obtain();
    Parcel localParcel2 = Parcel.obtain();
    try
    {
      localParcel1.writeInterfaceToken("com.google.android.gms.maps.model.internal.IPolygonDelegate");
      zzahn.transact(6, localParcel1, localParcel2, 0);
      localParcel2.readException();
      ArrayList localArrayList = localParcel2.readArrayList(getClass().getClassLoader());
      return localArrayList;
    }
    finally
    {
      localParcel2.recycle();
      localParcel1.recycle();
    }
  }
  
  public String getId()
    throws RemoteException
  {
    Parcel localParcel1 = Parcel.obtain();
    Parcel localParcel2 = Parcel.obtain();
    try
    {
      localParcel1.writeInterfaceToken("com.google.android.gms.maps.model.internal.IPolygonDelegate");
      zzahn.transact(2, localParcel1, localParcel2, 0);
      localParcel2.readException();
      String str = localParcel2.readString();
      return str;
    }
    finally
    {
      localParcel2.recycle();
      localParcel1.recycle();
    }
  }
  
  public List<LatLng> getPoints()
    throws RemoteException
  {
    Parcel localParcel1 = Parcel.obtain();
    Parcel localParcel2 = Parcel.obtain();
    try
    {
      localParcel1.writeInterfaceToken("com.google.android.gms.maps.model.internal.IPolygonDelegate");
      zzahn.transact(4, localParcel1, localParcel2, 0);
      localParcel2.readException();
      ArrayList localArrayList = localParcel2.createTypedArrayList(LatLng.CREATOR);
      return localArrayList;
    }
    finally
    {
      localParcel2.recycle();
      localParcel1.recycle();
    }
  }
  
  public int getStrokeColor()
    throws RemoteException
  {
    Parcel localParcel1 = Parcel.obtain();
    Parcel localParcel2 = Parcel.obtain();
    try
    {
      localParcel1.writeInterfaceToken("com.google.android.gms.maps.model.internal.IPolygonDelegate");
      zzahn.transact(10, localParcel1, localParcel2, 0);
      localParcel2.readException();
      int i = localParcel2.readInt();
      return i;
    }
    finally
    {
      localParcel2.recycle();
      localParcel1.recycle();
    }
  }
  
  public float getStrokeWidth()
    throws RemoteException
  {
    Parcel localParcel1 = Parcel.obtain();
    Parcel localParcel2 = Parcel.obtain();
    try
    {
      localParcel1.writeInterfaceToken("com.google.android.gms.maps.model.internal.IPolygonDelegate");
      zzahn.transact(8, localParcel1, localParcel2, 0);
      localParcel2.readException();
      float f = localParcel2.readFloat();
      return f;
    }
    finally
    {
      localParcel2.recycle();
      localParcel1.recycle();
    }
  }
  
  public float getZIndex()
    throws RemoteException
  {
    Parcel localParcel1 = Parcel.obtain();
    Parcel localParcel2 = Parcel.obtain();
    try
    {
      localParcel1.writeInterfaceToken("com.google.android.gms.maps.model.internal.IPolygonDelegate");
      zzahn.transact(14, localParcel1, localParcel2, 0);
      localParcel2.readException();
      float f = localParcel2.readFloat();
      return f;
    }
    finally
    {
      localParcel2.recycle();
      localParcel1.recycle();
    }
  }
  
  public int hashCodeRemote()
    throws RemoteException
  {
    Parcel localParcel1 = Parcel.obtain();
    Parcel localParcel2 = Parcel.obtain();
    try
    {
      localParcel1.writeInterfaceToken("com.google.android.gms.maps.model.internal.IPolygonDelegate");
      zzahn.transact(20, localParcel1, localParcel2, 0);
      localParcel2.readException();
      int i = localParcel2.readInt();
      return i;
    }
    finally
    {
      localParcel2.recycle();
      localParcel1.recycle();
    }
  }
  
  public boolean isClickable()
    throws RemoteException
  {
    boolean bool = false;
    Parcel localParcel1 = Parcel.obtain();
    Parcel localParcel2 = Parcel.obtain();
    try
    {
      localParcel1.writeInterfaceToken("com.google.android.gms.maps.model.internal.IPolygonDelegate");
      zzahn.transact(22, localParcel1, localParcel2, 0);
      localParcel2.readException();
      int i = localParcel2.readInt();
      if (i != 0) {
        bool = true;
      }
      return bool;
    }
    finally
    {
      localParcel2.recycle();
      localParcel1.recycle();
    }
  }
  
  public boolean isGeodesic()
    throws RemoteException
  {
    boolean bool = false;
    Parcel localParcel1 = Parcel.obtain();
    Parcel localParcel2 = Parcel.obtain();
    try
    {
      localParcel1.writeInterfaceToken("com.google.android.gms.maps.model.internal.IPolygonDelegate");
      zzahn.transact(18, localParcel1, localParcel2, 0);
      localParcel2.readException();
      int i = localParcel2.readInt();
      if (i != 0) {
        bool = true;
      }
      return bool;
    }
    finally
    {
      localParcel2.recycle();
      localParcel1.recycle();
    }
  }
  
  public boolean isVisible()
    throws RemoteException
  {
    boolean bool = false;
    Parcel localParcel1 = Parcel.obtain();
    Parcel localParcel2 = Parcel.obtain();
    try
    {
      localParcel1.writeInterfaceToken("com.google.android.gms.maps.model.internal.IPolygonDelegate");
      zzahn.transact(16, localParcel1, localParcel2, 0);
      localParcel2.readException();
      int i = localParcel2.readInt();
      if (i != 0) {
        bool = true;
      }
      return bool;
    }
    finally
    {
      localParcel2.recycle();
      localParcel1.recycle();
    }
  }
  
  public void remove()
    throws RemoteException
  {
    Parcel localParcel1 = Parcel.obtain();
    Parcel localParcel2 = Parcel.obtain();
    try
    {
      localParcel1.writeInterfaceToken("com.google.android.gms.maps.model.internal.IPolygonDelegate");
      zzahn.transact(1, localParcel1, localParcel2, 0);
      localParcel2.readException();
      return;
    }
    finally
    {
      localParcel2.recycle();
      localParcel1.recycle();
    }
  }
  
  public void setClickable(boolean paramBoolean)
    throws RemoteException
  {
    int i = 0;
    Parcel localParcel1 = Parcel.obtain();
    Parcel localParcel2 = Parcel.obtain();
    try
    {
      localParcel1.writeInterfaceToken("com.google.android.gms.maps.model.internal.IPolygonDelegate");
      if (paramBoolean) {
        i = 1;
      }
      localParcel1.writeInt(i);
      zzahn.transact(21, localParcel1, localParcel2, 0);
      localParcel2.readException();
      return;
    }
    finally
    {
      localParcel2.recycle();
      localParcel1.recycle();
    }
  }
  
  public void setFillColor(int paramInt)
    throws RemoteException
  {
    Parcel localParcel1 = Parcel.obtain();
    Parcel localParcel2 = Parcel.obtain();
    try
    {
      localParcel1.writeInterfaceToken("com.google.android.gms.maps.model.internal.IPolygonDelegate");
      localParcel1.writeInt(paramInt);
      zzahn.transact(11, localParcel1, localParcel2, 0);
      localParcel2.readException();
      return;
    }
    finally
    {
      localParcel2.recycle();
      localParcel1.recycle();
    }
  }
  
  public void setGeodesic(boolean paramBoolean)
    throws RemoteException
  {
    int i = 0;
    Parcel localParcel1 = Parcel.obtain();
    Parcel localParcel2 = Parcel.obtain();
    try
    {
      localParcel1.writeInterfaceToken("com.google.android.gms.maps.model.internal.IPolygonDelegate");
      if (paramBoolean) {
        i = 1;
      }
      localParcel1.writeInt(i);
      zzahn.transact(17, localParcel1, localParcel2, 0);
      localParcel2.readException();
      return;
    }
    finally
    {
      localParcel2.recycle();
      localParcel1.recycle();
    }
  }
  
  public void setHoles(List paramList)
    throws RemoteException
  {
    Parcel localParcel1 = Parcel.obtain();
    Parcel localParcel2 = Parcel.obtain();
    try
    {
      localParcel1.writeInterfaceToken("com.google.android.gms.maps.model.internal.IPolygonDelegate");
      localParcel1.writeList(paramList);
      zzahn.transact(5, localParcel1, localParcel2, 0);
      localParcel2.readException();
      return;
    }
    finally
    {
      localParcel2.recycle();
      localParcel1.recycle();
    }
  }
  
  public void setPoints(List<LatLng> paramList)
    throws RemoteException
  {
    Parcel localParcel1 = Parcel.obtain();
    Parcel localParcel2 = Parcel.obtain();
    try
    {
      localParcel1.writeInterfaceToken("com.google.android.gms.maps.model.internal.IPolygonDelegate");
      localParcel1.writeTypedList(paramList);
      zzahn.transact(3, localParcel1, localParcel2, 0);
      localParcel2.readException();
      return;
    }
    finally
    {
      localParcel2.recycle();
      localParcel1.recycle();
    }
  }
  
  public void setStrokeColor(int paramInt)
    throws RemoteException
  {
    Parcel localParcel1 = Parcel.obtain();
    Parcel localParcel2 = Parcel.obtain();
    try
    {
      localParcel1.writeInterfaceToken("com.google.android.gms.maps.model.internal.IPolygonDelegate");
      localParcel1.writeInt(paramInt);
      zzahn.transact(9, localParcel1, localParcel2, 0);
      localParcel2.readException();
      return;
    }
    finally
    {
      localParcel2.recycle();
      localParcel1.recycle();
    }
  }
  
  public void setStrokeWidth(float paramFloat)
    throws RemoteException
  {
    Parcel localParcel1 = Parcel.obtain();
    Parcel localParcel2 = Parcel.obtain();
    try
    {
      localParcel1.writeInterfaceToken("com.google.android.gms.maps.model.internal.IPolygonDelegate");
      localParcel1.writeFloat(paramFloat);
      zzahn.transact(7, localParcel1, localParcel2, 0);
      localParcel2.readException();
      return;
    }
    finally
    {
      localParcel2.recycle();
      localParcel1.recycle();
    }
  }
  
  public void setVisible(boolean paramBoolean)
    throws RemoteException
  {
    int i = 0;
    Parcel localParcel1 = Parcel.obtain();
    Parcel localParcel2 = Parcel.obtain();
    try
    {
      localParcel1.writeInterfaceToken("com.google.android.gms.maps.model.internal.IPolygonDelegate");
      if (paramBoolean) {
        i = 1;
      }
      localParcel1.writeInt(i);
      zzahn.transact(15, localParcel1, localParcel2, 0);
      localParcel2.readException();
      return;
    }
    finally
    {
      localParcel2.recycle();
      localParcel1.recycle();
    }
  }
  
  public void setZIndex(float paramFloat)
    throws RemoteException
  {
    Parcel localParcel1 = Parcel.obtain();
    Parcel localParcel2 = Parcel.obtain();
    try
    {
      localParcel1.writeInterfaceToken("com.google.android.gms.maps.model.internal.IPolygonDelegate");
      localParcel1.writeFloat(paramFloat);
      zzahn.transact(13, localParcel1, localParcel2, 0);
      localParcel2.readException();
      return;
    }
    finally
    {
      localParcel2.recycle();
      localParcel1.recycle();
    }
  }
  
  /* Error */
  public boolean zzb(zzg paramzzg)
    throws RemoteException
  {
    // Byte code:
    //   0: iconst_0
    //   1: istore_3
    //   2: invokestatic 31	android/os/Parcel:obtain	()Landroid/os/Parcel;
    //   5: astore 4
    //   7: invokestatic 31	android/os/Parcel:obtain	()Landroid/os/Parcel;
    //   10: astore 5
    //   12: aload 4
    //   14: ldc 33
    //   16: invokevirtual 37	android/os/Parcel:writeInterfaceToken	(Ljava/lang/String;)V
    //   19: aload_1
    //   20: ifnull +62 -> 82
    //   23: aload_1
    //   24: invokeinterface 130 1 0
    //   29: astore_1
    //   30: aload 4
    //   32: aload_1
    //   33: invokevirtual 133	android/os/Parcel:writeStrongBinder	(Landroid/os/IBinder;)V
    //   36: aload_0
    //   37: getfield 18	com/google/android/gms/maps/model/internal/zzg$zza$zza:zzahn	Landroid/os/IBinder;
    //   40: bipush 19
    //   42: aload 4
    //   44: aload 5
    //   46: iconst_0
    //   47: invokeinterface 43 5 0
    //   52: pop
    //   53: aload 5
    //   55: invokevirtual 46	android/os/Parcel:readException	()V
    //   58: aload 5
    //   60: invokevirtual 49	android/os/Parcel:readInt	()I
    //   63: istore_2
    //   64: iload_2
    //   65: ifeq +5 -> 70
    //   68: iconst_1
    //   69: istore_3
    //   70: aload 5
    //   72: invokevirtual 52	android/os/Parcel:recycle	()V
    //   75: aload 4
    //   77: invokevirtual 52	android/os/Parcel:recycle	()V
    //   80: iload_3
    //   81: ireturn
    //   82: aconst_null
    //   83: astore_1
    //   84: goto -54 -> 30
    //   87: astore_1
    //   88: aload 5
    //   90: invokevirtual 52	android/os/Parcel:recycle	()V
    //   93: aload 4
    //   95: invokevirtual 52	android/os/Parcel:recycle	()V
    //   98: aload_1
    //   99: athrow
    // Local variable table:
    //   start	length	slot	name	signature
    //   0	100	0	this	zza
    //   0	100	1	paramzzg	zzg
    //   63	2	2	i	int
    //   1	80	3	bool	boolean
    //   5	89	4	localParcel1	Parcel
    //   10	79	5	localParcel2	Parcel
    // Exception table:
    //   from	to	target	type
    //   12	19	87	finally
    //   23	30	87	finally
    //   30	64	87	finally
  }
}

/* Location:
 * Qualified Name:     com.google.android.gms.maps.model.internal.zzg.zza.zza
 * Java Class Version: 6 (50.0)
 * JD-Core Version:    0.7.1
 */