package com.google.android.gms.ads.internal.client;

import android.os.IBinder;
import android.os.Parcel;
import android.os.RemoteException;
import com.google.android.gms.dynamic.zzd;
import com.google.android.gms.dynamic.zzd.zza;

class zzu$zza$zza
  implements zzu
{
  private IBinder zzahn;
  
  zzu$zza$zza(IBinder paramIBinder)
  {
    zzahn = paramIBinder;
  }
  
  public IBinder asBinder()
  {
    return zzahn;
  }
  
  public void destroy()
    throws RemoteException
  {
    Parcel localParcel1 = Parcel.obtain();
    Parcel localParcel2 = Parcel.obtain();
    try
    {
      localParcel1.writeInterfaceToken("com.google.android.gms.ads.internal.client.IAdManager");
      zzahn.transact(2, localParcel1, localParcel2, 0);
      localParcel2.readException();
      return;
    }
    finally
    {
      localParcel2.recycle();
      localParcel1.recycle();
    }
  }
  
  public String getMediationAdapterClassName()
    throws RemoteException
  {
    Parcel localParcel1 = Parcel.obtain();
    Parcel localParcel2 = Parcel.obtain();
    try
    {
      localParcel1.writeInterfaceToken("com.google.android.gms.ads.internal.client.IAdManager");
      zzahn.transact(18, localParcel1, localParcel2, 0);
      localParcel2.readException();
      String str = localParcel2.readString();
      return str;
    }
    finally
    {
      localParcel2.recycle();
      localParcel1.recycle();
    }
  }
  
  public boolean isLoading()
    throws RemoteException
  {
    boolean bool = false;
    Parcel localParcel1 = Parcel.obtain();
    Parcel localParcel2 = Parcel.obtain();
    try
    {
      localParcel1.writeInterfaceToken("com.google.android.gms.ads.internal.client.IAdManager");
      zzahn.transact(23, localParcel1, localParcel2, 0);
      localParcel2.readException();
      int i = localParcel2.readInt();
      if (i != 0) {
        bool = true;
      }
      return bool;
    }
    finally
    {
      localParcel2.recycle();
      localParcel1.recycle();
    }
  }
  
  public boolean isReady()
    throws RemoteException
  {
    boolean bool = false;
    Parcel localParcel1 = Parcel.obtain();
    Parcel localParcel2 = Parcel.obtain();
    try
    {
      localParcel1.writeInterfaceToken("com.google.android.gms.ads.internal.client.IAdManager");
      zzahn.transact(3, localParcel1, localParcel2, 0);
      localParcel2.readException();
      int i = localParcel2.readInt();
      if (i != 0) {
        bool = true;
      }
      return bool;
    }
    finally
    {
      localParcel2.recycle();
      localParcel1.recycle();
    }
  }
  
  public void pause()
    throws RemoteException
  {
    Parcel localParcel1 = Parcel.obtain();
    Parcel localParcel2 = Parcel.obtain();
    try
    {
      localParcel1.writeInterfaceToken("com.google.android.gms.ads.internal.client.IAdManager");
      zzahn.transact(5, localParcel1, localParcel2, 0);
      localParcel2.readException();
      return;
    }
    finally
    {
      localParcel2.recycle();
      localParcel1.recycle();
    }
  }
  
  public void resume()
    throws RemoteException
  {
    Parcel localParcel1 = Parcel.obtain();
    Parcel localParcel2 = Parcel.obtain();
    try
    {
      localParcel1.writeInterfaceToken("com.google.android.gms.ads.internal.client.IAdManager");
      zzahn.transact(6, localParcel1, localParcel2, 0);
      localParcel2.readException();
      return;
    }
    finally
    {
      localParcel2.recycle();
      localParcel1.recycle();
    }
  }
  
  public void setManualImpressionsEnabled(boolean paramBoolean)
    throws RemoteException
  {
    int i = 0;
    Parcel localParcel1 = Parcel.obtain();
    Parcel localParcel2 = Parcel.obtain();
    try
    {
      localParcel1.writeInterfaceToken("com.google.android.gms.ads.internal.client.IAdManager");
      if (paramBoolean) {
        i = 1;
      }
      localParcel1.writeInt(i);
      zzahn.transact(22, localParcel1, localParcel2, 0);
      localParcel2.readException();
      return;
    }
    finally
    {
      localParcel2.recycle();
      localParcel1.recycle();
    }
  }
  
  public void setUserId(String paramString)
    throws RemoteException
  {
    Parcel localParcel1 = Parcel.obtain();
    Parcel localParcel2 = Parcel.obtain();
    try
    {
      localParcel1.writeInterfaceToken("com.google.android.gms.ads.internal.client.IAdManager");
      localParcel1.writeString(paramString);
      zzahn.transact(25, localParcel1, localParcel2, 0);
      localParcel2.readException();
      return;
    }
    finally
    {
      localParcel2.recycle();
      localParcel1.recycle();
    }
  }
  
  public void showInterstitial()
    throws RemoteException
  {
    Parcel localParcel1 = Parcel.obtain();
    Parcel localParcel2 = Parcel.obtain();
    try
    {
      localParcel1.writeInterfaceToken("com.google.android.gms.ads.internal.client.IAdManager");
      zzahn.transact(9, localParcel1, localParcel2, 0);
      localParcel2.readException();
      return;
    }
    finally
    {
      localParcel2.recycle();
      localParcel1.recycle();
    }
  }
  
  public void stopLoading()
    throws RemoteException
  {
    Parcel localParcel1 = Parcel.obtain();
    Parcel localParcel2 = Parcel.obtain();
    try
    {
      localParcel1.writeInterfaceToken("com.google.android.gms.ads.internal.client.IAdManager");
      zzahn.transact(10, localParcel1, localParcel2, 0);
      localParcel2.readException();
      return;
    }
    finally
    {
      localParcel2.recycle();
      localParcel1.recycle();
    }
  }
  
  /* Error */
  public void zza(AdSizeParcel paramAdSizeParcel)
    throws RemoteException
  {
    // Byte code:
    //   0: invokestatic 30	android/os/Parcel:obtain	()Landroid/os/Parcel;
    //   3: astore_2
    //   4: invokestatic 30	android/os/Parcel:obtain	()Landroid/os/Parcel;
    //   7: astore_3
    //   8: aload_2
    //   9: ldc 32
    //   11: invokevirtual 36	android/os/Parcel:writeInterfaceToken	(Ljava/lang/String;)V
    //   14: aload_1
    //   15: ifnull +42 -> 57
    //   18: aload_2
    //   19: iconst_1
    //   20: invokevirtual 69	android/os/Parcel:writeInt	(I)V
    //   23: aload_1
    //   24: aload_2
    //   25: iconst_0
    //   26: invokevirtual 82	com/google/android/gms/ads/internal/client/AdSizeParcel:writeToParcel	(Landroid/os/Parcel;I)V
    //   29: aload_0
    //   30: getfield 18	com/google/android/gms/ads/internal/client/zzu$zza$zza:zzahn	Landroid/os/IBinder;
    //   33: bipush 13
    //   35: aload_2
    //   36: aload_3
    //   37: iconst_0
    //   38: invokeinterface 42 5 0
    //   43: pop
    //   44: aload_3
    //   45: invokevirtual 45	android/os/Parcel:readException	()V
    //   48: aload_3
    //   49: invokevirtual 48	android/os/Parcel:recycle	()V
    //   52: aload_2
    //   53: invokevirtual 48	android/os/Parcel:recycle	()V
    //   56: return
    //   57: aload_2
    //   58: iconst_0
    //   59: invokevirtual 69	android/os/Parcel:writeInt	(I)V
    //   62: goto -33 -> 29
    //   65: astore_1
    //   66: aload_3
    //   67: invokevirtual 48	android/os/Parcel:recycle	()V
    //   70: aload_2
    //   71: invokevirtual 48	android/os/Parcel:recycle	()V
    //   74: aload_1
    //   75: athrow
    // Local variable table:
    //   start	length	slot	name	signature
    //   0	76	0	this	zza
    //   0	76	1	paramAdSizeParcel	AdSizeParcel
    //   3	68	2	localParcel1	Parcel
    //   7	60	3	localParcel2	Parcel
    // Exception table:
    //   from	to	target	type
    //   8	14	65	finally
    //   18	29	65	finally
    //   29	48	65	finally
    //   57	62	65	finally
  }
  
  /* Error */
  public void zza(VideoOptionsParcel paramVideoOptionsParcel)
    throws RemoteException
  {
    // Byte code:
    //   0: invokestatic 30	android/os/Parcel:obtain	()Landroid/os/Parcel;
    //   3: astore_2
    //   4: invokestatic 30	android/os/Parcel:obtain	()Landroid/os/Parcel;
    //   7: astore_3
    //   8: aload_2
    //   9: ldc 32
    //   11: invokevirtual 36	android/os/Parcel:writeInterfaceToken	(Ljava/lang/String;)V
    //   14: aload_1
    //   15: ifnull +42 -> 57
    //   18: aload_2
    //   19: iconst_1
    //   20: invokevirtual 69	android/os/Parcel:writeInt	(I)V
    //   23: aload_1
    //   24: aload_2
    //   25: iconst_0
    //   26: invokevirtual 86	com/google/android/gms/ads/internal/client/VideoOptionsParcel:writeToParcel	(Landroid/os/Parcel;I)V
    //   29: aload_0
    //   30: getfield 18	com/google/android/gms/ads/internal/client/zzu$zza$zza:zzahn	Landroid/os/IBinder;
    //   33: bipush 29
    //   35: aload_2
    //   36: aload_3
    //   37: iconst_0
    //   38: invokeinterface 42 5 0
    //   43: pop
    //   44: aload_3
    //   45: invokevirtual 45	android/os/Parcel:readException	()V
    //   48: aload_3
    //   49: invokevirtual 48	android/os/Parcel:recycle	()V
    //   52: aload_2
    //   53: invokevirtual 48	android/os/Parcel:recycle	()V
    //   56: return
    //   57: aload_2
    //   58: iconst_0
    //   59: invokevirtual 69	android/os/Parcel:writeInt	(I)V
    //   62: goto -33 -> 29
    //   65: astore_1
    //   66: aload_3
    //   67: invokevirtual 48	android/os/Parcel:recycle	()V
    //   70: aload_2
    //   71: invokevirtual 48	android/os/Parcel:recycle	()V
    //   74: aload_1
    //   75: athrow
    // Local variable table:
    //   start	length	slot	name	signature
    //   0	76	0	this	zza
    //   0	76	1	paramVideoOptionsParcel	VideoOptionsParcel
    //   3	68	2	localParcel1	Parcel
    //   7	60	3	localParcel2	Parcel
    // Exception table:
    //   from	to	target	type
    //   8	14	65	finally
    //   18	29	65	finally
    //   29	48	65	finally
    //   57	62	65	finally
  }
  
  /* Error */
  public void zza(zzp paramzzp)
    throws RemoteException
  {
    // Byte code:
    //   0: invokestatic 30	android/os/Parcel:obtain	()Landroid/os/Parcel;
    //   3: astore_2
    //   4: invokestatic 30	android/os/Parcel:obtain	()Landroid/os/Parcel;
    //   7: astore_3
    //   8: aload_2
    //   9: ldc 32
    //   11: invokevirtual 36	android/os/Parcel:writeInterfaceToken	(Ljava/lang/String;)V
    //   14: aload_1
    //   15: ifnull +43 -> 58
    //   18: aload_1
    //   19: invokeinterface 91 1 0
    //   24: astore_1
    //   25: aload_2
    //   26: aload_1
    //   27: invokevirtual 94	android/os/Parcel:writeStrongBinder	(Landroid/os/IBinder;)V
    //   30: aload_0
    //   31: getfield 18	com/google/android/gms/ads/internal/client/zzu$zza$zza:zzahn	Landroid/os/IBinder;
    //   34: bipush 20
    //   36: aload_2
    //   37: aload_3
    //   38: iconst_0
    //   39: invokeinterface 42 5 0
    //   44: pop
    //   45: aload_3
    //   46: invokevirtual 45	android/os/Parcel:readException	()V
    //   49: aload_3
    //   50: invokevirtual 48	android/os/Parcel:recycle	()V
    //   53: aload_2
    //   54: invokevirtual 48	android/os/Parcel:recycle	()V
    //   57: return
    //   58: aconst_null
    //   59: astore_1
    //   60: goto -35 -> 25
    //   63: astore_1
    //   64: aload_3
    //   65: invokevirtual 48	android/os/Parcel:recycle	()V
    //   68: aload_2
    //   69: invokevirtual 48	android/os/Parcel:recycle	()V
    //   72: aload_1
    //   73: athrow
    // Local variable table:
    //   start	length	slot	name	signature
    //   0	74	0	this	zza
    //   0	74	1	paramzzp	zzp
    //   3	66	2	localParcel1	Parcel
    //   7	58	3	localParcel2	Parcel
    // Exception table:
    //   from	to	target	type
    //   8	14	63	finally
    //   18	25	63	finally
    //   25	49	63	finally
  }
  
  /* Error */
  public void zza(zzq paramzzq)
    throws RemoteException
  {
    // Byte code:
    //   0: invokestatic 30	android/os/Parcel:obtain	()Landroid/os/Parcel;
    //   3: astore_2
    //   4: invokestatic 30	android/os/Parcel:obtain	()Landroid/os/Parcel;
    //   7: astore_3
    //   8: aload_2
    //   9: ldc 32
    //   11: invokevirtual 36	android/os/Parcel:writeInterfaceToken	(Ljava/lang/String;)V
    //   14: aload_1
    //   15: ifnull +43 -> 58
    //   18: aload_1
    //   19: invokeinterface 98 1 0
    //   24: astore_1
    //   25: aload_2
    //   26: aload_1
    //   27: invokevirtual 94	android/os/Parcel:writeStrongBinder	(Landroid/os/IBinder;)V
    //   30: aload_0
    //   31: getfield 18	com/google/android/gms/ads/internal/client/zzu$zza$zza:zzahn	Landroid/os/IBinder;
    //   34: bipush 7
    //   36: aload_2
    //   37: aload_3
    //   38: iconst_0
    //   39: invokeinterface 42 5 0
    //   44: pop
    //   45: aload_3
    //   46: invokevirtual 45	android/os/Parcel:readException	()V
    //   49: aload_3
    //   50: invokevirtual 48	android/os/Parcel:recycle	()V
    //   53: aload_2
    //   54: invokevirtual 48	android/os/Parcel:recycle	()V
    //   57: return
    //   58: aconst_null
    //   59: astore_1
    //   60: goto -35 -> 25
    //   63: astore_1
    //   64: aload_3
    //   65: invokevirtual 48	android/os/Parcel:recycle	()V
    //   68: aload_2
    //   69: invokevirtual 48	android/os/Parcel:recycle	()V
    //   72: aload_1
    //   73: athrow
    // Local variable table:
    //   start	length	slot	name	signature
    //   0	74	0	this	zza
    //   0	74	1	paramzzq	zzq
    //   3	66	2	localParcel1	Parcel
    //   7	58	3	localParcel2	Parcel
    // Exception table:
    //   from	to	target	type
    //   8	14	63	finally
    //   18	25	63	finally
    //   25	49	63	finally
  }
  
  /* Error */
  public void zza(zzw paramzzw)
    throws RemoteException
  {
    // Byte code:
    //   0: invokestatic 30	android/os/Parcel:obtain	()Landroid/os/Parcel;
    //   3: astore_2
    //   4: invokestatic 30	android/os/Parcel:obtain	()Landroid/os/Parcel;
    //   7: astore_3
    //   8: aload_2
    //   9: ldc 32
    //   11: invokevirtual 36	android/os/Parcel:writeInterfaceToken	(Ljava/lang/String;)V
    //   14: aload_1
    //   15: ifnull +43 -> 58
    //   18: aload_1
    //   19: invokeinterface 102 1 0
    //   24: astore_1
    //   25: aload_2
    //   26: aload_1
    //   27: invokevirtual 94	android/os/Parcel:writeStrongBinder	(Landroid/os/IBinder;)V
    //   30: aload_0
    //   31: getfield 18	com/google/android/gms/ads/internal/client/zzu$zza$zza:zzahn	Landroid/os/IBinder;
    //   34: bipush 8
    //   36: aload_2
    //   37: aload_3
    //   38: iconst_0
    //   39: invokeinterface 42 5 0
    //   44: pop
    //   45: aload_3
    //   46: invokevirtual 45	android/os/Parcel:readException	()V
    //   49: aload_3
    //   50: invokevirtual 48	android/os/Parcel:recycle	()V
    //   53: aload_2
    //   54: invokevirtual 48	android/os/Parcel:recycle	()V
    //   57: return
    //   58: aconst_null
    //   59: astore_1
    //   60: goto -35 -> 25
    //   63: astore_1
    //   64: aload_3
    //   65: invokevirtual 48	android/os/Parcel:recycle	()V
    //   68: aload_2
    //   69: invokevirtual 48	android/os/Parcel:recycle	()V
    //   72: aload_1
    //   73: athrow
    // Local variable table:
    //   start	length	slot	name	signature
    //   0	74	0	this	zza
    //   0	74	1	paramzzw	zzw
    //   3	66	2	localParcel1	Parcel
    //   7	58	3	localParcel2	Parcel
    // Exception table:
    //   from	to	target	type
    //   8	14	63	finally
    //   18	25	63	finally
    //   25	49	63	finally
  }
  
  /* Error */
  public void zza(zzy paramzzy)
    throws RemoteException
  {
    // Byte code:
    //   0: invokestatic 30	android/os/Parcel:obtain	()Landroid/os/Parcel;
    //   3: astore_2
    //   4: invokestatic 30	android/os/Parcel:obtain	()Landroid/os/Parcel;
    //   7: astore_3
    //   8: aload_2
    //   9: ldc 32
    //   11: invokevirtual 36	android/os/Parcel:writeInterfaceToken	(Ljava/lang/String;)V
    //   14: aload_1
    //   15: ifnull +43 -> 58
    //   18: aload_1
    //   19: invokeinterface 106 1 0
    //   24: astore_1
    //   25: aload_2
    //   26: aload_1
    //   27: invokevirtual 94	android/os/Parcel:writeStrongBinder	(Landroid/os/IBinder;)V
    //   30: aload_0
    //   31: getfield 18	com/google/android/gms/ads/internal/client/zzu$zza$zza:zzahn	Landroid/os/IBinder;
    //   34: bipush 21
    //   36: aload_2
    //   37: aload_3
    //   38: iconst_0
    //   39: invokeinterface 42 5 0
    //   44: pop
    //   45: aload_3
    //   46: invokevirtual 45	android/os/Parcel:readException	()V
    //   49: aload_3
    //   50: invokevirtual 48	android/os/Parcel:recycle	()V
    //   53: aload_2
    //   54: invokevirtual 48	android/os/Parcel:recycle	()V
    //   57: return
    //   58: aconst_null
    //   59: astore_1
    //   60: goto -35 -> 25
    //   63: astore_1
    //   64: aload_3
    //   65: invokevirtual 48	android/os/Parcel:recycle	()V
    //   68: aload_2
    //   69: invokevirtual 48	android/os/Parcel:recycle	()V
    //   72: aload_1
    //   73: athrow
    // Local variable table:
    //   start	length	slot	name	signature
    //   0	74	0	this	zza
    //   0	74	1	paramzzy	zzy
    //   3	66	2	localParcel1	Parcel
    //   7	58	3	localParcel2	Parcel
    // Exception table:
    //   from	to	target	type
    //   8	14	63	finally
    //   18	25	63	finally
    //   25	49	63	finally
  }
  
  /* Error */
  public void zza(com.google.android.gms.ads.internal.reward.client.zzd paramzzd)
    throws RemoteException
  {
    // Byte code:
    //   0: invokestatic 30	android/os/Parcel:obtain	()Landroid/os/Parcel;
    //   3: astore_2
    //   4: invokestatic 30	android/os/Parcel:obtain	()Landroid/os/Parcel;
    //   7: astore_3
    //   8: aload_2
    //   9: ldc 32
    //   11: invokevirtual 36	android/os/Parcel:writeInterfaceToken	(Ljava/lang/String;)V
    //   14: aload_1
    //   15: ifnull +43 -> 58
    //   18: aload_1
    //   19: invokeinterface 110 1 0
    //   24: astore_1
    //   25: aload_2
    //   26: aload_1
    //   27: invokevirtual 94	android/os/Parcel:writeStrongBinder	(Landroid/os/IBinder;)V
    //   30: aload_0
    //   31: getfield 18	com/google/android/gms/ads/internal/client/zzu$zza$zza:zzahn	Landroid/os/IBinder;
    //   34: bipush 24
    //   36: aload_2
    //   37: aload_3
    //   38: iconst_0
    //   39: invokeinterface 42 5 0
    //   44: pop
    //   45: aload_3
    //   46: invokevirtual 45	android/os/Parcel:readException	()V
    //   49: aload_3
    //   50: invokevirtual 48	android/os/Parcel:recycle	()V
    //   53: aload_2
    //   54: invokevirtual 48	android/os/Parcel:recycle	()V
    //   57: return
    //   58: aconst_null
    //   59: astore_1
    //   60: goto -35 -> 25
    //   63: astore_1
    //   64: aload_3
    //   65: invokevirtual 48	android/os/Parcel:recycle	()V
    //   68: aload_2
    //   69: invokevirtual 48	android/os/Parcel:recycle	()V
    //   72: aload_1
    //   73: athrow
    // Local variable table:
    //   start	length	slot	name	signature
    //   0	74	0	this	zza
    //   0	74	1	paramzzd	com.google.android.gms.ads.internal.reward.client.zzd
    //   3	66	2	localParcel1	Parcel
    //   7	58	3	localParcel2	Parcel
    // Exception table:
    //   from	to	target	type
    //   8	14	63	finally
    //   18	25	63	finally
    //   25	49	63	finally
  }
  
  /* Error */
  public void zza(com.google.android.gms.internal.zzdo paramzzdo)
    throws RemoteException
  {
    // Byte code:
    //   0: invokestatic 30	android/os/Parcel:obtain	()Landroid/os/Parcel;
    //   3: astore_2
    //   4: invokestatic 30	android/os/Parcel:obtain	()Landroid/os/Parcel;
    //   7: astore_3
    //   8: aload_2
    //   9: ldc 32
    //   11: invokevirtual 36	android/os/Parcel:writeInterfaceToken	(Ljava/lang/String;)V
    //   14: aload_1
    //   15: ifnull +43 -> 58
    //   18: aload_1
    //   19: invokeinterface 114 1 0
    //   24: astore_1
    //   25: aload_2
    //   26: aload_1
    //   27: invokevirtual 94	android/os/Parcel:writeStrongBinder	(Landroid/os/IBinder;)V
    //   30: aload_0
    //   31: getfield 18	com/google/android/gms/ads/internal/client/zzu$zza$zza:zzahn	Landroid/os/IBinder;
    //   34: bipush 19
    //   36: aload_2
    //   37: aload_3
    //   38: iconst_0
    //   39: invokeinterface 42 5 0
    //   44: pop
    //   45: aload_3
    //   46: invokevirtual 45	android/os/Parcel:readException	()V
    //   49: aload_3
    //   50: invokevirtual 48	android/os/Parcel:recycle	()V
    //   53: aload_2
    //   54: invokevirtual 48	android/os/Parcel:recycle	()V
    //   57: return
    //   58: aconst_null
    //   59: astore_1
    //   60: goto -35 -> 25
    //   63: astore_1
    //   64: aload_3
    //   65: invokevirtual 48	android/os/Parcel:recycle	()V
    //   68: aload_2
    //   69: invokevirtual 48	android/os/Parcel:recycle	()V
    //   72: aload_1
    //   73: athrow
    // Local variable table:
    //   start	length	slot	name	signature
    //   0	74	0	this	zza
    //   0	74	1	paramzzdo	com.google.android.gms.internal.zzdo
    //   3	66	2	localParcel1	Parcel
    //   7	58	3	localParcel2	Parcel
    // Exception table:
    //   from	to	target	type
    //   8	14	63	finally
    //   18	25	63	finally
    //   25	49	63	finally
  }
  
  /* Error */
  public void zza(com.google.android.gms.internal.zzhs paramzzhs)
    throws RemoteException
  {
    // Byte code:
    //   0: invokestatic 30	android/os/Parcel:obtain	()Landroid/os/Parcel;
    //   3: astore_2
    //   4: invokestatic 30	android/os/Parcel:obtain	()Landroid/os/Parcel;
    //   7: astore_3
    //   8: aload_2
    //   9: ldc 32
    //   11: invokevirtual 36	android/os/Parcel:writeInterfaceToken	(Ljava/lang/String;)V
    //   14: aload_1
    //   15: ifnull +43 -> 58
    //   18: aload_1
    //   19: invokeinterface 118 1 0
    //   24: astore_1
    //   25: aload_2
    //   26: aload_1
    //   27: invokevirtual 94	android/os/Parcel:writeStrongBinder	(Landroid/os/IBinder;)V
    //   30: aload_0
    //   31: getfield 18	com/google/android/gms/ads/internal/client/zzu$zza$zza:zzahn	Landroid/os/IBinder;
    //   34: bipush 14
    //   36: aload_2
    //   37: aload_3
    //   38: iconst_0
    //   39: invokeinterface 42 5 0
    //   44: pop
    //   45: aload_3
    //   46: invokevirtual 45	android/os/Parcel:readException	()V
    //   49: aload_3
    //   50: invokevirtual 48	android/os/Parcel:recycle	()V
    //   53: aload_2
    //   54: invokevirtual 48	android/os/Parcel:recycle	()V
    //   57: return
    //   58: aconst_null
    //   59: astore_1
    //   60: goto -35 -> 25
    //   63: astore_1
    //   64: aload_3
    //   65: invokevirtual 48	android/os/Parcel:recycle	()V
    //   68: aload_2
    //   69: invokevirtual 48	android/os/Parcel:recycle	()V
    //   72: aload_1
    //   73: athrow
    // Local variable table:
    //   start	length	slot	name	signature
    //   0	74	0	this	zza
    //   0	74	1	paramzzhs	com.google.android.gms.internal.zzhs
    //   3	66	2	localParcel1	Parcel
    //   7	58	3	localParcel2	Parcel
    // Exception table:
    //   from	to	target	type
    //   8	14	63	finally
    //   18	25	63	finally
    //   25	49	63	finally
  }
  
  /* Error */
  public void zza(com.google.android.gms.internal.zzhw paramzzhw, String paramString)
    throws RemoteException
  {
    // Byte code:
    //   0: invokestatic 30	android/os/Parcel:obtain	()Landroid/os/Parcel;
    //   3: astore_3
    //   4: invokestatic 30	android/os/Parcel:obtain	()Landroid/os/Parcel;
    //   7: astore 4
    //   9: aload_3
    //   10: ldc 32
    //   12: invokevirtual 36	android/os/Parcel:writeInterfaceToken	(Ljava/lang/String;)V
    //   15: aload_1
    //   16: ifnull +51 -> 67
    //   19: aload_1
    //   20: invokeinterface 122 1 0
    //   25: astore_1
    //   26: aload_3
    //   27: aload_1
    //   28: invokevirtual 94	android/os/Parcel:writeStrongBinder	(Landroid/os/IBinder;)V
    //   31: aload_3
    //   32: aload_2
    //   33: invokevirtual 73	android/os/Parcel:writeString	(Ljava/lang/String;)V
    //   36: aload_0
    //   37: getfield 18	com/google/android/gms/ads/internal/client/zzu$zza$zza:zzahn	Landroid/os/IBinder;
    //   40: bipush 15
    //   42: aload_3
    //   43: aload 4
    //   45: iconst_0
    //   46: invokeinterface 42 5 0
    //   51: pop
    //   52: aload 4
    //   54: invokevirtual 45	android/os/Parcel:readException	()V
    //   57: aload 4
    //   59: invokevirtual 48	android/os/Parcel:recycle	()V
    //   62: aload_3
    //   63: invokevirtual 48	android/os/Parcel:recycle	()V
    //   66: return
    //   67: aconst_null
    //   68: astore_1
    //   69: goto -43 -> 26
    //   72: astore_1
    //   73: aload 4
    //   75: invokevirtual 48	android/os/Parcel:recycle	()V
    //   78: aload_3
    //   79: invokevirtual 48	android/os/Parcel:recycle	()V
    //   82: aload_1
    //   83: athrow
    // Local variable table:
    //   start	length	slot	name	signature
    //   0	84	0	this	zza
    //   0	84	1	paramzzhw	com.google.android.gms.internal.zzhw
    //   0	84	2	paramString	String
    //   3	76	3	localParcel1	Parcel
    //   7	67	4	localParcel2	Parcel
    // Exception table:
    //   from	to	target	type
    //   9	15	72	finally
    //   19	26	72	finally
    //   26	57	72	finally
  }
  
  public boolean zzb(AdRequestParcel paramAdRequestParcel)
    throws RemoteException
  {
    boolean bool = true;
    Parcel localParcel1 = Parcel.obtain();
    Parcel localParcel2 = Parcel.obtain();
    for (;;)
    {
      try
      {
        localParcel1.writeInterfaceToken("com.google.android.gms.ads.internal.client.IAdManager");
        if (paramAdRequestParcel != null)
        {
          localParcel1.writeInt(1);
          paramAdRequestParcel.writeToParcel(localParcel1, 0);
          zzahn.transact(4, localParcel1, localParcel2, 0);
          localParcel2.readException();
          int i = localParcel2.readInt();
          if (i != 0) {
            return bool;
          }
        }
        else
        {
          localParcel1.writeInt(0);
          continue;
        }
        bool = false;
      }
      finally
      {
        localParcel2.recycle();
        localParcel1.recycle();
      }
    }
  }
  
  public zzd zzdn()
    throws RemoteException
  {
    Parcel localParcel1 = Parcel.obtain();
    Parcel localParcel2 = Parcel.obtain();
    try
    {
      localParcel1.writeInterfaceToken("com.google.android.gms.ads.internal.client.IAdManager");
      zzahn.transact(1, localParcel1, localParcel2, 0);
      localParcel2.readException();
      zzd localzzd = zzd.zza.zzfc(localParcel2.readStrongBinder());
      return localzzd;
    }
    finally
    {
      localParcel2.recycle();
      localParcel1.recycle();
    }
  }
  
  /* Error */
  public AdSizeParcel zzdo()
    throws RemoteException
  {
    // Byte code:
    //   0: invokestatic 30	android/os/Parcel:obtain	()Landroid/os/Parcel;
    //   3: astore_2
    //   4: invokestatic 30	android/os/Parcel:obtain	()Landroid/os/Parcel;
    //   7: astore_3
    //   8: aload_2
    //   9: ldc 32
    //   11: invokevirtual 36	android/os/Parcel:writeInterfaceToken	(Ljava/lang/String;)V
    //   14: aload_0
    //   15: getfield 18	com/google/android/gms/ads/internal/client/zzu$zza$zza:zzahn	Landroid/os/IBinder;
    //   18: bipush 12
    //   20: aload_2
    //   21: aload_3
    //   22: iconst_0
    //   23: invokeinterface 42 5 0
    //   28: pop
    //   29: aload_3
    //   30: invokevirtual 45	android/os/Parcel:readException	()V
    //   33: aload_3
    //   34: invokevirtual 60	android/os/Parcel:readInt	()I
    //   37: ifeq +24 -> 61
    //   40: getstatic 144	com/google/android/gms/ads/internal/client/AdSizeParcel:CREATOR	Lcom/google/android/gms/ads/internal/client/zzi;
    //   43: aload_3
    //   44: invokevirtual 150	com/google/android/gms/ads/internal/client/zzi:createFromParcel	(Landroid/os/Parcel;)Ljava/lang/Object;
    //   47: checkcast 78	com/google/android/gms/ads/internal/client/AdSizeParcel
    //   50: astore_1
    //   51: aload_3
    //   52: invokevirtual 48	android/os/Parcel:recycle	()V
    //   55: aload_2
    //   56: invokevirtual 48	android/os/Parcel:recycle	()V
    //   59: aload_1
    //   60: areturn
    //   61: aconst_null
    //   62: astore_1
    //   63: goto -12 -> 51
    //   66: astore_1
    //   67: aload_3
    //   68: invokevirtual 48	android/os/Parcel:recycle	()V
    //   71: aload_2
    //   72: invokevirtual 48	android/os/Parcel:recycle	()V
    //   75: aload_1
    //   76: athrow
    // Local variable table:
    //   start	length	slot	name	signature
    //   0	77	0	this	zza
    //   50	13	1	localAdSizeParcel	AdSizeParcel
    //   66	10	1	localObject	Object
    //   3	69	2	localParcel1	Parcel
    //   7	61	3	localParcel2	Parcel
    // Exception table:
    //   from	to	target	type
    //   8	51	66	finally
  }
  
  public void zzdq()
    throws RemoteException
  {
    Parcel localParcel1 = Parcel.obtain();
    Parcel localParcel2 = Parcel.obtain();
    try
    {
      localParcel1.writeInterfaceToken("com.google.android.gms.ads.internal.client.IAdManager");
      zzahn.transact(11, localParcel1, localParcel2, 0);
      localParcel2.readException();
      return;
    }
    finally
    {
      localParcel2.recycle();
      localParcel1.recycle();
    }
  }
  
  public zzab zzdr()
    throws RemoteException
  {
    Parcel localParcel1 = Parcel.obtain();
    Parcel localParcel2 = Parcel.obtain();
    try
    {
      localParcel1.writeInterfaceToken("com.google.android.gms.ads.internal.client.IAdManager");
      zzahn.transact(26, localParcel1, localParcel2, 0);
      localParcel2.readException();
      zzab localzzab = zzab.zza.zzt(localParcel2.readStrongBinder());
      return localzzab;
    }
    finally
    {
      localParcel2.recycle();
      localParcel1.recycle();
    }
  }
}

/* Location:
 * Qualified Name:     com.google.android.gms.ads.internal.client.zzu.zza.zza
 * Java Class Version: 6 (50.0)
 * JD-Core Version:    0.7.1
 */