package com.google.android.gms.wearable.internal;

import android.os.IBinder;
import android.os.Parcel;
import android.os.RemoteException;
import java.util.List;

class zzaw$zza$zza
  implements zzaw
{
  private IBinder zzahn;
  
  zzaw$zza$zza(IBinder paramIBinder)
  {
    zzahn = paramIBinder;
  }
  
  public IBinder asBinder()
  {
    return zzahn;
  }
  
  public void onConnectedNodes(List<NodeParcelable> paramList)
    throws RemoteException
  {
    Parcel localParcel = Parcel.obtain();
    try
    {
      localParcel.writeInterfaceToken("com.google.android.gms.wearable.internal.IWearableListener");
      localParcel.writeTypedList(paramList);
      zzahn.transact(5, localParcel, null, 1);
      return;
    }
    finally
    {
      localParcel.recycle();
    }
  }
  
  /* Error */
  public void zza(AmsEntityUpdateParcelable paramAmsEntityUpdateParcelable)
    throws RemoteException
  {
    // Byte code:
    //   0: invokestatic 31	android/os/Parcel:obtain	()Landroid/os/Parcel;
    //   3: astore_2
    //   4: aload_2
    //   5: ldc 33
    //   7: invokevirtual 37	android/os/Parcel:writeInterfaceToken	(Ljava/lang/String;)V
    //   10: aload_1
    //   11: ifnull +34 -> 45
    //   14: aload_2
    //   15: iconst_1
    //   16: invokevirtual 57	android/os/Parcel:writeInt	(I)V
    //   19: aload_1
    //   20: aload_2
    //   21: iconst_0
    //   22: invokevirtual 63	com/google/android/gms/wearable/internal/AmsEntityUpdateParcelable:writeToParcel	(Landroid/os/Parcel;I)V
    //   25: aload_0
    //   26: getfield 18	com/google/android/gms/wearable/internal/zzaw$zza$zza:zzahn	Landroid/os/IBinder;
    //   29: bipush 9
    //   31: aload_2
    //   32: aconst_null
    //   33: iconst_1
    //   34: invokeinterface 46 5 0
    //   39: pop
    //   40: aload_2
    //   41: invokevirtual 49	android/os/Parcel:recycle	()V
    //   44: return
    //   45: aload_2
    //   46: iconst_0
    //   47: invokevirtual 57	android/os/Parcel:writeInt	(I)V
    //   50: goto -25 -> 25
    //   53: astore_1
    //   54: aload_2
    //   55: invokevirtual 49	android/os/Parcel:recycle	()V
    //   58: aload_1
    //   59: athrow
    // Local variable table:
    //   start	length	slot	name	signature
    //   0	60	0	this	zza
    //   0	60	1	paramAmsEntityUpdateParcelable	AmsEntityUpdateParcelable
    //   3	52	2	localParcel	Parcel
    // Exception table:
    //   from	to	target	type
    //   4	10	53	finally
    //   14	25	53	finally
    //   25	40	53	finally
    //   45	50	53	finally
  }
  
  /* Error */
  public void zza(AncsNotificationParcelable paramAncsNotificationParcelable)
    throws RemoteException
  {
    // Byte code:
    //   0: invokestatic 31	android/os/Parcel:obtain	()Landroid/os/Parcel;
    //   3: astore_2
    //   4: aload_2
    //   5: ldc 33
    //   7: invokevirtual 37	android/os/Parcel:writeInterfaceToken	(Ljava/lang/String;)V
    //   10: aload_1
    //   11: ifnull +34 -> 45
    //   14: aload_2
    //   15: iconst_1
    //   16: invokevirtual 57	android/os/Parcel:writeInt	(I)V
    //   19: aload_1
    //   20: aload_2
    //   21: iconst_0
    //   22: invokevirtual 67	com/google/android/gms/wearable/internal/AncsNotificationParcelable:writeToParcel	(Landroid/os/Parcel;I)V
    //   25: aload_0
    //   26: getfield 18	com/google/android/gms/wearable/internal/zzaw$zza$zza:zzahn	Landroid/os/IBinder;
    //   29: bipush 6
    //   31: aload_2
    //   32: aconst_null
    //   33: iconst_1
    //   34: invokeinterface 46 5 0
    //   39: pop
    //   40: aload_2
    //   41: invokevirtual 49	android/os/Parcel:recycle	()V
    //   44: return
    //   45: aload_2
    //   46: iconst_0
    //   47: invokevirtual 57	android/os/Parcel:writeInt	(I)V
    //   50: goto -25 -> 25
    //   53: astore_1
    //   54: aload_2
    //   55: invokevirtual 49	android/os/Parcel:recycle	()V
    //   58: aload_1
    //   59: athrow
    // Local variable table:
    //   start	length	slot	name	signature
    //   0	60	0	this	zza
    //   0	60	1	paramAncsNotificationParcelable	AncsNotificationParcelable
    //   3	52	2	localParcel	Parcel
    // Exception table:
    //   from	to	target	type
    //   4	10	53	finally
    //   14	25	53	finally
    //   25	40	53	finally
    //   45	50	53	finally
  }
  
  /* Error */
  public void zza(CapabilityInfoParcelable paramCapabilityInfoParcelable)
    throws RemoteException
  {
    // Byte code:
    //   0: invokestatic 31	android/os/Parcel:obtain	()Landroid/os/Parcel;
    //   3: astore_2
    //   4: aload_2
    //   5: ldc 33
    //   7: invokevirtual 37	android/os/Parcel:writeInterfaceToken	(Ljava/lang/String;)V
    //   10: aload_1
    //   11: ifnull +34 -> 45
    //   14: aload_2
    //   15: iconst_1
    //   16: invokevirtual 57	android/os/Parcel:writeInt	(I)V
    //   19: aload_1
    //   20: aload_2
    //   21: iconst_0
    //   22: invokevirtual 71	com/google/android/gms/wearable/internal/CapabilityInfoParcelable:writeToParcel	(Landroid/os/Parcel;I)V
    //   25: aload_0
    //   26: getfield 18	com/google/android/gms/wearable/internal/zzaw$zza$zza:zzahn	Landroid/os/IBinder;
    //   29: bipush 8
    //   31: aload_2
    //   32: aconst_null
    //   33: iconst_1
    //   34: invokeinterface 46 5 0
    //   39: pop
    //   40: aload_2
    //   41: invokevirtual 49	android/os/Parcel:recycle	()V
    //   44: return
    //   45: aload_2
    //   46: iconst_0
    //   47: invokevirtual 57	android/os/Parcel:writeInt	(I)V
    //   50: goto -25 -> 25
    //   53: astore_1
    //   54: aload_2
    //   55: invokevirtual 49	android/os/Parcel:recycle	()V
    //   58: aload_1
    //   59: athrow
    // Local variable table:
    //   start	length	slot	name	signature
    //   0	60	0	this	zza
    //   0	60	1	paramCapabilityInfoParcelable	CapabilityInfoParcelable
    //   3	52	2	localParcel	Parcel
    // Exception table:
    //   from	to	target	type
    //   4	10	53	finally
    //   14	25	53	finally
    //   25	40	53	finally
    //   45	50	53	finally
  }
  
  /* Error */
  public void zza(ChannelEventParcelable paramChannelEventParcelable)
    throws RemoteException
  {
    // Byte code:
    //   0: invokestatic 31	android/os/Parcel:obtain	()Landroid/os/Parcel;
    //   3: astore_2
    //   4: aload_2
    //   5: ldc 33
    //   7: invokevirtual 37	android/os/Parcel:writeInterfaceToken	(Ljava/lang/String;)V
    //   10: aload_1
    //   11: ifnull +34 -> 45
    //   14: aload_2
    //   15: iconst_1
    //   16: invokevirtual 57	android/os/Parcel:writeInt	(I)V
    //   19: aload_1
    //   20: aload_2
    //   21: iconst_0
    //   22: invokevirtual 75	com/google/android/gms/wearable/internal/ChannelEventParcelable:writeToParcel	(Landroid/os/Parcel;I)V
    //   25: aload_0
    //   26: getfield 18	com/google/android/gms/wearable/internal/zzaw$zza$zza:zzahn	Landroid/os/IBinder;
    //   29: bipush 7
    //   31: aload_2
    //   32: aconst_null
    //   33: iconst_1
    //   34: invokeinterface 46 5 0
    //   39: pop
    //   40: aload_2
    //   41: invokevirtual 49	android/os/Parcel:recycle	()V
    //   44: return
    //   45: aload_2
    //   46: iconst_0
    //   47: invokevirtual 57	android/os/Parcel:writeInt	(I)V
    //   50: goto -25 -> 25
    //   53: astore_1
    //   54: aload_2
    //   55: invokevirtual 49	android/os/Parcel:recycle	()V
    //   58: aload_1
    //   59: athrow
    // Local variable table:
    //   start	length	slot	name	signature
    //   0	60	0	this	zza
    //   0	60	1	paramChannelEventParcelable	ChannelEventParcelable
    //   3	52	2	localParcel	Parcel
    // Exception table:
    //   from	to	target	type
    //   4	10	53	finally
    //   14	25	53	finally
    //   25	40	53	finally
    //   45	50	53	finally
  }
  
  /* Error */
  public void zza(MessageEventParcelable paramMessageEventParcelable)
    throws RemoteException
  {
    // Byte code:
    //   0: invokestatic 31	android/os/Parcel:obtain	()Landroid/os/Parcel;
    //   3: astore_2
    //   4: aload_2
    //   5: ldc 33
    //   7: invokevirtual 37	android/os/Parcel:writeInterfaceToken	(Ljava/lang/String;)V
    //   10: aload_1
    //   11: ifnull +33 -> 44
    //   14: aload_2
    //   15: iconst_1
    //   16: invokevirtual 57	android/os/Parcel:writeInt	(I)V
    //   19: aload_1
    //   20: aload_2
    //   21: iconst_0
    //   22: invokevirtual 79	com/google/android/gms/wearable/internal/MessageEventParcelable:writeToParcel	(Landroid/os/Parcel;I)V
    //   25: aload_0
    //   26: getfield 18	com/google/android/gms/wearable/internal/zzaw$zza$zza:zzahn	Landroid/os/IBinder;
    //   29: iconst_2
    //   30: aload_2
    //   31: aconst_null
    //   32: iconst_1
    //   33: invokeinterface 46 5 0
    //   38: pop
    //   39: aload_2
    //   40: invokevirtual 49	android/os/Parcel:recycle	()V
    //   43: return
    //   44: aload_2
    //   45: iconst_0
    //   46: invokevirtual 57	android/os/Parcel:writeInt	(I)V
    //   49: goto -24 -> 25
    //   52: astore_1
    //   53: aload_2
    //   54: invokevirtual 49	android/os/Parcel:recycle	()V
    //   57: aload_1
    //   58: athrow
    // Local variable table:
    //   start	length	slot	name	signature
    //   0	59	0	this	zza
    //   0	59	1	paramMessageEventParcelable	MessageEventParcelable
    //   3	51	2	localParcel	Parcel
    // Exception table:
    //   from	to	target	type
    //   4	10	52	finally
    //   14	25	52	finally
    //   25	39	52	finally
    //   44	49	52	finally
  }
  
  /* Error */
  public void zza(NodeParcelable paramNodeParcelable)
    throws RemoteException
  {
    // Byte code:
    //   0: invokestatic 31	android/os/Parcel:obtain	()Landroid/os/Parcel;
    //   3: astore_2
    //   4: aload_2
    //   5: ldc 33
    //   7: invokevirtual 37	android/os/Parcel:writeInterfaceToken	(Ljava/lang/String;)V
    //   10: aload_1
    //   11: ifnull +33 -> 44
    //   14: aload_2
    //   15: iconst_1
    //   16: invokevirtual 57	android/os/Parcel:writeInt	(I)V
    //   19: aload_1
    //   20: aload_2
    //   21: iconst_0
    //   22: invokevirtual 83	com/google/android/gms/wearable/internal/NodeParcelable:writeToParcel	(Landroid/os/Parcel;I)V
    //   25: aload_0
    //   26: getfield 18	com/google/android/gms/wearable/internal/zzaw$zza$zza:zzahn	Landroid/os/IBinder;
    //   29: iconst_3
    //   30: aload_2
    //   31: aconst_null
    //   32: iconst_1
    //   33: invokeinterface 46 5 0
    //   38: pop
    //   39: aload_2
    //   40: invokevirtual 49	android/os/Parcel:recycle	()V
    //   43: return
    //   44: aload_2
    //   45: iconst_0
    //   46: invokevirtual 57	android/os/Parcel:writeInt	(I)V
    //   49: goto -24 -> 25
    //   52: astore_1
    //   53: aload_2
    //   54: invokevirtual 49	android/os/Parcel:recycle	()V
    //   57: aload_1
    //   58: athrow
    // Local variable table:
    //   start	length	slot	name	signature
    //   0	59	0	this	zza
    //   0	59	1	paramNodeParcelable	NodeParcelable
    //   3	51	2	localParcel	Parcel
    // Exception table:
    //   from	to	target	type
    //   4	10	52	finally
    //   14	25	52	finally
    //   25	39	52	finally
    //   44	49	52	finally
  }
  
  /* Error */
  public void zzb(NodeParcelable paramNodeParcelable)
    throws RemoteException
  {
    // Byte code:
    //   0: invokestatic 31	android/os/Parcel:obtain	()Landroid/os/Parcel;
    //   3: astore_2
    //   4: aload_2
    //   5: ldc 33
    //   7: invokevirtual 37	android/os/Parcel:writeInterfaceToken	(Ljava/lang/String;)V
    //   10: aload_1
    //   11: ifnull +33 -> 44
    //   14: aload_2
    //   15: iconst_1
    //   16: invokevirtual 57	android/os/Parcel:writeInt	(I)V
    //   19: aload_1
    //   20: aload_2
    //   21: iconst_0
    //   22: invokevirtual 83	com/google/android/gms/wearable/internal/NodeParcelable:writeToParcel	(Landroid/os/Parcel;I)V
    //   25: aload_0
    //   26: getfield 18	com/google/android/gms/wearable/internal/zzaw$zza$zza:zzahn	Landroid/os/IBinder;
    //   29: iconst_4
    //   30: aload_2
    //   31: aconst_null
    //   32: iconst_1
    //   33: invokeinterface 46 5 0
    //   38: pop
    //   39: aload_2
    //   40: invokevirtual 49	android/os/Parcel:recycle	()V
    //   43: return
    //   44: aload_2
    //   45: iconst_0
    //   46: invokevirtual 57	android/os/Parcel:writeInt	(I)V
    //   49: goto -24 -> 25
    //   52: astore_1
    //   53: aload_2
    //   54: invokevirtual 49	android/os/Parcel:recycle	()V
    //   57: aload_1
    //   58: athrow
    // Local variable table:
    //   start	length	slot	name	signature
    //   0	59	0	this	zza
    //   0	59	1	paramNodeParcelable	NodeParcelable
    //   3	51	2	localParcel	Parcel
    // Exception table:
    //   from	to	target	type
    //   4	10	52	finally
    //   14	25	52	finally
    //   25	39	52	finally
    //   44	49	52	finally
  }
  
  /* Error */
  public void zzbq(com.google.android.gms.common.data.DataHolder paramDataHolder)
    throws RemoteException
  {
    // Byte code:
    //   0: invokestatic 31	android/os/Parcel:obtain	()Landroid/os/Parcel;
    //   3: astore_2
    //   4: aload_2
    //   5: ldc 33
    //   7: invokevirtual 37	android/os/Parcel:writeInterfaceToken	(Ljava/lang/String;)V
    //   10: aload_1
    //   11: ifnull +33 -> 44
    //   14: aload_2
    //   15: iconst_1
    //   16: invokevirtual 57	android/os/Parcel:writeInt	(I)V
    //   19: aload_1
    //   20: aload_2
    //   21: iconst_0
    //   22: invokevirtual 89	com/google/android/gms/common/data/DataHolder:writeToParcel	(Landroid/os/Parcel;I)V
    //   25: aload_0
    //   26: getfield 18	com/google/android/gms/wearable/internal/zzaw$zza$zza:zzahn	Landroid/os/IBinder;
    //   29: iconst_1
    //   30: aload_2
    //   31: aconst_null
    //   32: iconst_1
    //   33: invokeinterface 46 5 0
    //   38: pop
    //   39: aload_2
    //   40: invokevirtual 49	android/os/Parcel:recycle	()V
    //   43: return
    //   44: aload_2
    //   45: iconst_0
    //   46: invokevirtual 57	android/os/Parcel:writeInt	(I)V
    //   49: goto -24 -> 25
    //   52: astore_1
    //   53: aload_2
    //   54: invokevirtual 49	android/os/Parcel:recycle	()V
    //   57: aload_1
    //   58: athrow
    // Local variable table:
    //   start	length	slot	name	signature
    //   0	59	0	this	zza
    //   0	59	1	paramDataHolder	com.google.android.gms.common.data.DataHolder
    //   3	51	2	localParcel	Parcel
    // Exception table:
    //   from	to	target	type
    //   4	10	52	finally
    //   14	25	52	finally
    //   25	39	52	finally
    //   44	49	52	finally
  }
}

/* Location:
 * Qualified Name:     com.google.android.gms.wearable.internal.zzaw.zza.zza
 * Java Class Version: 6 (50.0)
 * JD-Core Version:    0.7.1
 */