package bo.app;

import com.appboy.Constants;
import java.util.Map;

public final class dz
  implements Runnable
{
  private static final String a = String.format("%s.%s", new Object[] { Constants.APPBOY_LOG_TAG_PREFIX, dz.class.getName() });
  private final ee b;
  private final bd c;
  private final bd d;
  private final Map<String, String> e;
  private final h f;
  private final ex g;
  private final fb h;
  private final ch i;
  
  public dz(ee paramee, f paramf, h paramh, bd parambd1, bd parambd2, ex paramex, ch paramch, fb paramfb)
  {
    b = paramee;
    c = parambd1;
    d = parambd2;
    e = paramf.a();
    f = paramh;
    g = paramex;
    i = paramch;
    h = paramfb;
  }
  
  /* Error */
  public final void run()
  {
    // Byte code:
    //   0: aload_0
    //   1: getfield 54	bo/app/dz:b	Lbo/app/ee;
    //   4: invokeinterface 83 1 0
    //   9: invokestatic 88	bo/app/fi:a	(Landroid/net/Uri;)Ljava/net/URI;
    //   12: astore 4
    //   14: getstatic 93	bo/app/ea:a	[I
    //   17: aload_0
    //   18: getfield 54	bo/app/dz:b	Lbo/app/ee;
    //   21: invokeinterface 96 1 0
    //   26: invokevirtual 102	bo/app/af:ordinal	()I
    //   29: iaload
    //   30: tableswitch	default:+1206->1236, 1:+807->837, 2:+902->932
    //   52: getstatic 47	bo/app/dz:a	Ljava/lang/String;
    //   55: ldc 104
    //   57: iconst_1
    //   58: anewarray 4	java/lang/Object
    //   61: dup
    //   62: iconst_0
    //   63: aload_0
    //   64: getfield 54	bo/app/dz:b	Lbo/app/ee;
    //   67: invokeinterface 96 1 0
    //   72: aastore
    //   73: invokestatic 45	java/lang/String:format	(Ljava/lang/String;[Ljava/lang/Object;)Ljava/lang/String;
    //   76: invokestatic 110	com/appboy/support/AppboyLogger:w	(Ljava/lang/String;Ljava/lang/String;)I
    //   79: pop
    //   80: aconst_null
    //   81: astore 4
    //   83: aload 4
    //   85: ifnull +1138 -> 1223
    //   88: aload 4
    //   90: getfield 115	bo/app/co:a	Lbo/app/cy;
    //   93: astore 6
    //   95: aload 4
    //   97: getfield 118	bo/app/co:b	Lbo/app/cz;
    //   100: astore 4
    //   102: aload 4
    //   104: ifnull +1135 -> 1239
    //   107: aload 4
    //   109: getfield 123	bo/app/cz:a	Lcom/appboy/models/ResponseError;
    //   112: astore 4
    //   114: aload 4
    //   116: ifnonnull +881 -> 997
    //   119: aload_0
    //   120: getfield 54	bo/app/dz:b	Lbo/app/ee;
    //   123: aload_0
    //   124: getfield 58	bo/app/dz:d	Lbo/app/bd;
    //   127: invokeinterface 126 2 0
    //   132: aload 6
    //   134: ifnull +666 -> 800
    //   137: aload_0
    //   138: getfield 65	bo/app/dz:e	Ljava/util/Map;
    //   141: ldc -128
    //   143: invokeinterface 134 2 0
    //   148: checkcast 41	java/lang/String
    //   151: astore 5
    //   153: aload 6
    //   155: getfield 139	bo/app/cy:a	Lorg/json/JSONArray;
    //   158: astore 4
    //   160: aload 4
    //   162: ifnull +938 -> 1100
    //   165: iconst_1
    //   166: istore_1
    //   167: iload_1
    //   168: ifeq +221 -> 389
    //   171: aload_0
    //   172: getfield 69	bo/app/dz:g	Lbo/app/ex;
    //   175: astore 7
    //   177: aload 6
    //   179: getfield 139	bo/app/cy:a	Lorg/json/JSONArray;
    //   182: astore 8
    //   184: aload 5
    //   186: ifnonnull +919 -> 1105
    //   189: ldc -115
    //   191: astore 4
    //   193: aload 7
    //   195: getfield 146	bo/app/ex:b	Landroid/content/SharedPreferences;
    //   198: ldc -108
    //   200: ldc -115
    //   202: invokeinterface 154 3 0
    //   207: astore 9
    //   209: aload 9
    //   211: aload 4
    //   213: invokevirtual 158	java/lang/String:equals	(Ljava/lang/Object;)Z
    //   216: ifeq +929 -> 1145
    //   219: getstatic 159	bo/app/ex:a	Ljava/lang/String;
    //   222: new 161	java/lang/StringBuilder
    //   225: dup
    //   226: ldc -93
    //   228: invokespecial 166	java/lang/StringBuilder:<init>	(Ljava/lang/String;)V
    //   231: aload 5
    //   233: invokevirtual 170	java/lang/StringBuilder:append	(Ljava/lang/String;)Ljava/lang/StringBuilder;
    //   236: invokevirtual 173	java/lang/StringBuilder:toString	()Ljava/lang/String;
    //   239: invokestatic 175	com/appboy/support/AppboyLogger:i	(Ljava/lang/String;Ljava/lang/String;)I
    //   242: pop
    //   243: invokestatic 180	bo/app/fg:a	()J
    //   246: lstore_2
    //   247: aload 7
    //   249: getfield 146	bo/app/ex:b	Landroid/content/SharedPreferences;
    //   252: invokeinterface 184 1 0
    //   257: astore 4
    //   259: aload 8
    //   261: ifnull +11 -> 272
    //   264: aload 8
    //   266: invokevirtual 189	org/json/JSONArray:length	()I
    //   269: ifne +843 -> 1112
    //   272: aload 4
    //   274: ldc -65
    //   276: invokeinterface 197 2 0
    //   281: pop
    //   282: aload 4
    //   284: ldc -57
    //   286: lload_2
    //   287: invokeinterface 203 4 0
    //   292: pop
    //   293: aload 4
    //   295: invokeinterface 206 1 0
    //   300: aload 7
    //   302: getfield 209	bo/app/ex:c	Ljava/util/Set;
    //   305: aload 8
    //   307: invokestatic 212	bo/app/ex:a	(Lorg/json/JSONArray;)Ljava/util/Set;
    //   310: invokeinterface 218 2 0
    //   315: pop
    //   316: aload 7
    //   318: aload 7
    //   320: getfield 209	bo/app/ex:c	Ljava/util/Set;
    //   323: getstatic 223	bo/app/ey:b	Lbo/app/ey;
    //   326: invokevirtual 226	bo/app/ex:a	(Ljava/util/Set;Lbo/app/ey;)V
    //   329: aload 7
    //   331: getfield 228	bo/app/ex:d	Ljava/util/Set;
    //   334: aload 8
    //   336: invokestatic 212	bo/app/ex:a	(Lorg/json/JSONArray;)Ljava/util/Set;
    //   339: invokeinterface 218 2 0
    //   344: pop
    //   345: aload 7
    //   347: aload 7
    //   349: getfield 228	bo/app/ex:d	Ljava/util/Set;
    //   352: getstatic 230	bo/app/ey:a	Lbo/app/ey;
    //   355: invokevirtual 226	bo/app/ex:a	(Ljava/util/Set;Lbo/app/ey;)V
    //   358: aload 7
    //   360: aload 8
    //   362: aload 5
    //   364: iconst_0
    //   365: lload_2
    //   366: invokevirtual 233	bo/app/ex:a	(Lorg/json/JSONArray;Ljava/lang/String;ZJ)Lcom/appboy/events/FeedUpdatedEvent;
    //   369: astore 4
    //   371: aload 4
    //   373: ifnull +16 -> 389
    //   376: aload_0
    //   377: getfield 58	bo/app/dz:d	Lbo/app/bd;
    //   380: aload 4
    //   382: ldc -21
    //   384: invokeinterface 240 3 0
    //   389: aload 6
    //   391: getfield 243	bo/app/cy:d	Lbo/app/da;
    //   394: ifnull +799 -> 1193
    //   397: iconst_1
    //   398: istore_1
    //   399: iload_1
    //   400: ifeq +310 -> 710
    //   403: aload_0
    //   404: getfield 73	bo/app/dz:h	Lbo/app/fb;
    //   407: astore 7
    //   409: aload 6
    //   411: getfield 243	bo/app/cy:d	Lbo/app/da;
    //   414: astore 4
    //   416: aload 7
    //   418: getfield 248	bo/app/fb:d	Ljava/lang/Object;
    //   421: astore 5
    //   423: aload 5
    //   425: monitorenter
    //   426: aload 4
    //   428: getfield 253	bo/app/da:i	Z
    //   431: ifeq +27 -> 458
    //   434: aload 7
    //   436: invokevirtual 256	bo/app/fb:a	()Z
    //   439: ifne +19 -> 458
    //   442: aload 7
    //   444: getfield 258	bo/app/fb:b	Lbo/app/bd;
    //   447: getstatic 263	bo/app/dx:a	Lbo/app/dx;
    //   450: ldc_w 260
    //   453: invokeinterface 240 3 0
    //   458: aload 7
    //   460: aload 4
    //   462: putfield 265	bo/app/fb:f	Lbo/app/da;
    //   465: aload 5
    //   467: monitorexit
    //   468: aload 7
    //   470: getfield 267	bo/app/fb:c	Landroid/content/SharedPreferences;
    //   473: invokeinterface 184 1 0
    //   478: astore 5
    //   480: aload 4
    //   482: getfield 269	bo/app/da:b	Ljava/util/Set;
    //   485: ifnull +29 -> 514
    //   488: aload 5
    //   490: ldc_w 271
    //   493: new 186	org/json/JSONArray
    //   496: dup
    //   497: aload 4
    //   499: getfield 269	bo/app/da:b	Ljava/util/Set;
    //   502: invokespecial 274	org/json/JSONArray:<init>	(Ljava/util/Collection;)V
    //   505: invokevirtual 275	org/json/JSONArray:toString	()Ljava/lang/String;
    //   508: invokeinterface 279 3 0
    //   513: pop
    //   514: aload 4
    //   516: getfield 280	bo/app/da:c	Ljava/util/Set;
    //   519: ifnull +29 -> 548
    //   522: aload 5
    //   524: ldc_w 282
    //   527: new 186	org/json/JSONArray
    //   530: dup
    //   531: aload 4
    //   533: getfield 280	bo/app/da:c	Ljava/util/Set;
    //   536: invokespecial 274	org/json/JSONArray:<init>	(Ljava/util/Collection;)V
    //   539: invokevirtual 275	org/json/JSONArray:toString	()Ljava/lang/String;
    //   542: invokeinterface 279 3 0
    //   547: pop
    //   548: aload 4
    //   550: getfield 283	bo/app/da:d	Ljava/util/Set;
    //   553: ifnull +29 -> 582
    //   556: aload 5
    //   558: ldc_w 285
    //   561: new 186	org/json/JSONArray
    //   564: dup
    //   565: aload 4
    //   567: getfield 283	bo/app/da:d	Ljava/util/Set;
    //   570: invokespecial 274	org/json/JSONArray:<init>	(Ljava/util/Collection;)V
    //   573: invokevirtual 275	org/json/JSONArray:toString	()Ljava/lang/String;
    //   576: invokeinterface 279 3 0
    //   581: pop
    //   582: aload 5
    //   584: ldc_w 287
    //   587: aload 4
    //   589: getfield 290	bo/app/da:a	J
    //   592: invokeinterface 203 4 0
    //   597: pop
    //   598: aload 5
    //   600: ldc_w 292
    //   603: aload 4
    //   605: getfield 294	bo/app/da:f	Z
    //   608: invokeinterface 298 3 0
    //   613: pop
    //   614: aload 5
    //   616: ldc_w 300
    //   619: aload 4
    //   621: getfield 302	bo/app/da:e	Z
    //   624: invokeinterface 298 3 0
    //   629: pop
    //   630: aload 5
    //   632: ldc_w 304
    //   635: aload 4
    //   637: getfield 306	bo/app/da:g	J
    //   640: invokeinterface 203 4 0
    //   645: pop
    //   646: aload 5
    //   648: ldc_w 308
    //   651: aload 4
    //   653: getfield 311	bo/app/da:h	F
    //   656: invokeinterface 315 3 0
    //   661: pop
    //   662: aload 5
    //   664: ldc_w 317
    //   667: aload 4
    //   669: getfield 253	bo/app/da:i	Z
    //   672: invokeinterface 298 3 0
    //   677: pop
    //   678: aload 5
    //   680: invokeinterface 320 1 0
    //   685: pop
    //   686: aload_0
    //   687: getfield 56	bo/app/dz:c	Lbo/app/bd;
    //   690: new 322	bo/app/bj
    //   693: dup
    //   694: aload 6
    //   696: getfield 243	bo/app/cy:d	Lbo/app/da;
    //   699: invokespecial 325	bo/app/bj:<init>	(Lbo/app/da;)V
    //   702: ldc_w 322
    //   705: invokeinterface 240 3 0
    //   710: aload 6
    //   712: getfield 328	bo/app/cy:b	Lcom/appboy/models/IInAppMessage;
    //   715: ifnull +530 -> 1245
    //   718: iconst_1
    //   719: istore_1
    //   720: iload_1
    //   721: ifeq +41 -> 762
    //   724: aload_0
    //   725: getfield 58	bo/app/dz:d	Lbo/app/bd;
    //   728: new 330	com/appboy/events/InAppMessageEvent
    //   731: dup
    //   732: aload 6
    //   734: getfield 328	bo/app/cy:b	Lcom/appboy/models/IInAppMessage;
    //   737: aload_0
    //   738: getfield 65	bo/app/dz:e	Ljava/util/Map;
    //   741: ldc -128
    //   743: invokeinterface 134 2 0
    //   748: checkcast 41	java/lang/String
    //   751: invokespecial 333	com/appboy/events/InAppMessageEvent:<init>	(Lcom/appboy/models/IInAppMessage;Ljava/lang/String;)V
    //   754: ldc_w 330
    //   757: invokeinterface 240 3 0
    //   762: aload 6
    //   764: getfield 336	bo/app/cy:c	Ljava/util/List;
    //   767: ifnull +483 -> 1250
    //   770: iconst_1
    //   771: istore_1
    //   772: iload_1
    //   773: ifeq +27 -> 800
    //   776: aload_0
    //   777: getfield 56	bo/app/dz:c	Lbo/app/bd;
    //   780: new 338	bo/app/bo
    //   783: dup
    //   784: aload 6
    //   786: getfield 336	bo/app/cy:c	Ljava/util/List;
    //   789: invokespecial 341	bo/app/bo:<init>	(Ljava/util/List;)V
    //   792: ldc_w 338
    //   795: invokeinterface 240 3 0
    //   800: aload_0
    //   801: getfield 54	bo/app/dz:b	Lbo/app/ee;
    //   804: aload_0
    //   805: getfield 56	bo/app/dz:c	Lbo/app/bd;
    //   808: invokeinterface 343 2 0
    //   813: aload_0
    //   814: getfield 56	bo/app/dz:c	Lbo/app/bd;
    //   817: new 345	bo/app/bf
    //   820: dup
    //   821: aload_0
    //   822: getfield 54	bo/app/dz:b	Lbo/app/ee;
    //   825: invokespecial 348	bo/app/bf:<init>	(Lbo/app/ee;)V
    //   828: ldc_w 345
    //   831: invokeinterface 240 3 0
    //   836: return
    //   837: new 112	bo/app/co
    //   840: dup
    //   841: aload_0
    //   842: getfield 67	bo/app/dz:f	Lbo/app/h;
    //   845: aload 4
    //   847: aload_0
    //   848: getfield 65	bo/app/dz:e	Ljava/util/Map;
    //   851: invokeinterface 353 3 0
    //   856: aload_0
    //   857: getfield 71	bo/app/dz:i	Lbo/app/ch;
    //   860: invokespecial 356	bo/app/co:<init>	(Lorg/json/JSONObject;Lbo/app/ch;)V
    //   863: astore 4
    //   865: goto -782 -> 83
    //   868: astore 4
    //   870: getstatic 47	bo/app/dz:a	Ljava/lang/String;
    //   873: ldc_w 358
    //   876: aload 4
    //   878: invokestatic 361	com/appboy/support/AppboyLogger:w	(Ljava/lang/String;Ljava/lang/String;Ljava/lang/Throwable;)I
    //   881: pop
    //   882: aload_0
    //   883: getfield 54	bo/app/dz:b	Lbo/app/ee;
    //   886: aload_0
    //   887: getfield 58	bo/app/dz:d	Lbo/app/bd;
    //   890: new 363	com/appboy/models/ResponseError
    //   893: dup
    //   894: getstatic 369	com/appboy/enums/ErrorType:UNRECOGNIZED_ERROR	Lcom/appboy/enums/ErrorType;
    //   897: ldc_w 371
    //   900: invokespecial 374	com/appboy/models/ResponseError:<init>	(Lcom/appboy/enums/ErrorType;Ljava/lang/String;)V
    //   903: invokeinterface 377 3 0
    //   908: aload_0
    //   909: getfield 56	bo/app/dz:c	Lbo/app/bd;
    //   912: new 379	bo/app/be
    //   915: dup
    //   916: aload_0
    //   917: getfield 54	bo/app/dz:b	Lbo/app/ee;
    //   920: invokespecial 380	bo/app/be:<init>	(Lbo/app/ee;)V
    //   923: ldc_w 379
    //   926: invokeinterface 240 3 0
    //   931: return
    //   932: aload_0
    //   933: getfield 54	bo/app/dz:b	Lbo/app/ee;
    //   936: invokeinterface 383 1 0
    //   941: astore 5
    //   943: aload 5
    //   945: ifnonnull +19 -> 964
    //   948: getstatic 47	bo/app/dz:a	Ljava/lang/String;
    //   951: ldc_w 385
    //   954: invokestatic 387	com/appboy/support/AppboyLogger:e	(Ljava/lang/String;Ljava/lang/String;)I
    //   957: pop
    //   958: aconst_null
    //   959: astore 4
    //   961: goto -878 -> 83
    //   964: new 112	bo/app/co
    //   967: dup
    //   968: aload_0
    //   969: getfield 67	bo/app/dz:f	Lbo/app/h;
    //   972: aload 4
    //   974: aload_0
    //   975: getfield 65	bo/app/dz:e	Ljava/util/Map;
    //   978: aload 5
    //   980: invokeinterface 390 4 0
    //   985: aload_0
    //   986: getfield 71	bo/app/dz:i	Lbo/app/ch;
    //   989: invokespecial 356	bo/app/co:<init>	(Lorg/json/JSONObject;Lbo/app/ch;)V
    //   992: astore 4
    //   994: goto -911 -> 83
    //   997: aload 4
    //   999: invokevirtual 394	com/appboy/models/ResponseError:getType	()Lcom/appboy/enums/ErrorType;
    //   1002: astore 5
    //   1004: aload 5
    //   1006: getstatic 397	com/appboy/enums/ErrorType:NO_DEVICE_IDENTIFIER	Lcom/appboy/enums/ErrorType;
    //   1009: if_acmpne +31 -> 1040
    //   1012: getstatic 47	bo/app/dz:a	Ljava/lang/String;
    //   1015: ldc_w 399
    //   1018: invokestatic 387	com/appboy/support/AppboyLogger:e	(Ljava/lang/String;Ljava/lang/String;)I
    //   1021: pop
    //   1022: aload_0
    //   1023: getfield 54	bo/app/dz:b	Lbo/app/ee;
    //   1026: aload_0
    //   1027: getfield 58	bo/app/dz:d	Lbo/app/bd;
    //   1030: aload 4
    //   1032: invokeinterface 377 3 0
    //   1037: goto -905 -> 132
    //   1040: aload 5
    //   1042: getstatic 402	com/appboy/enums/ErrorType:INVALID_API_KEY	Lcom/appboy/enums/ErrorType;
    //   1045: if_acmpne +16 -> 1061
    //   1048: getstatic 47	bo/app/dz:a	Ljava/lang/String;
    //   1051: ldc_w 404
    //   1054: invokestatic 387	com/appboy/support/AppboyLogger:e	(Ljava/lang/String;Ljava/lang/String;)I
    //   1057: pop
    //   1058: goto -36 -> 1022
    //   1061: aload 5
    //   1063: getstatic 369	com/appboy/enums/ErrorType:UNRECOGNIZED_ERROR	Lcom/appboy/enums/ErrorType;
    //   1066: if_acmpne -44 -> 1022
    //   1069: getstatic 47	bo/app/dz:a	Ljava/lang/String;
    //   1072: new 161	java/lang/StringBuilder
    //   1075: dup
    //   1076: ldc_w 406
    //   1079: invokespecial 166	java/lang/StringBuilder:<init>	(Ljava/lang/String;)V
    //   1082: aload 4
    //   1084: invokevirtual 409	com/appboy/models/ResponseError:getMessage	()Ljava/lang/String;
    //   1087: invokevirtual 170	java/lang/StringBuilder:append	(Ljava/lang/String;)Ljava/lang/StringBuilder;
    //   1090: invokevirtual 173	java/lang/StringBuilder:toString	()Ljava/lang/String;
    //   1093: invokestatic 387	com/appboy/support/AppboyLogger:e	(Ljava/lang/String;Ljava/lang/String;)I
    //   1096: pop
    //   1097: goto -75 -> 1022
    //   1100: iconst_0
    //   1101: istore_1
    //   1102: goto -935 -> 167
    //   1105: aload 5
    //   1107: astore 4
    //   1109: goto -916 -> 193
    //   1112: aload 4
    //   1114: ldc -65
    //   1116: aload 8
    //   1118: invokevirtual 275	org/json/JSONArray:toString	()Ljava/lang/String;
    //   1121: invokeinterface 279 3 0
    //   1126: pop
    //   1127: goto -845 -> 282
    //   1130: astore 4
    //   1132: getstatic 47	bo/app/dz:a	Ljava/lang/String;
    //   1135: ldc_w 411
    //   1138: invokestatic 110	com/appboy/support/AppboyLogger:w	(Ljava/lang/String;Ljava/lang/String;)I
    //   1141: pop
    //   1142: goto -753 -> 389
    //   1145: getstatic 159	bo/app/ex:a	Ljava/lang/String;
    //   1148: new 161	java/lang/StringBuilder
    //   1151: dup
    //   1152: ldc_w 413
    //   1155: invokespecial 166	java/lang/StringBuilder:<init>	(Ljava/lang/String;)V
    //   1158: aload 5
    //   1160: invokevirtual 170	java/lang/StringBuilder:append	(Ljava/lang/String;)Ljava/lang/StringBuilder;
    //   1163: ldc_w 415
    //   1166: invokevirtual 170	java/lang/StringBuilder:append	(Ljava/lang/String;)Ljava/lang/StringBuilder;
    //   1169: aload 9
    //   1171: invokevirtual 170	java/lang/StringBuilder:append	(Ljava/lang/String;)Ljava/lang/StringBuilder;
    //   1174: ldc_w 417
    //   1177: invokevirtual 170	java/lang/StringBuilder:append	(Ljava/lang/String;)Ljava/lang/StringBuilder;
    //   1180: invokevirtual 173	java/lang/StringBuilder:toString	()Ljava/lang/String;
    //   1183: invokestatic 175	com/appboy/support/AppboyLogger:i	(Ljava/lang/String;Ljava/lang/String;)I
    //   1186: pop
    //   1187: aconst_null
    //   1188: astore 4
    //   1190: goto -819 -> 371
    //   1193: iconst_0
    //   1194: istore_1
    //   1195: goto -796 -> 399
    //   1198: astore 4
    //   1200: aload 5
    //   1202: monitorexit
    //   1203: aload 4
    //   1205: athrow
    //   1206: astore 4
    //   1208: getstatic 418	bo/app/fb:a	Ljava/lang/String;
    //   1211: ldc_w 420
    //   1214: aload 4
    //   1216: invokestatic 361	com/appboy/support/AppboyLogger:w	(Ljava/lang/String;Ljava/lang/String;Ljava/lang/Throwable;)I
    //   1219: pop
    //   1220: goto -534 -> 686
    //   1223: getstatic 47	bo/app/dz:a	Ljava/lang/String;
    //   1226: ldc_w 422
    //   1229: invokestatic 110	com/appboy/support/AppboyLogger:w	(Ljava/lang/String;Ljava/lang/String;)I
    //   1232: pop
    //   1233: goto -351 -> 882
    //   1236: goto -1184 -> 52
    //   1239: aconst_null
    //   1240: astore 4
    //   1242: goto -1128 -> 114
    //   1245: iconst_0
    //   1246: istore_1
    //   1247: goto -527 -> 720
    //   1250: iconst_0
    //   1251: istore_1
    //   1252: goto -480 -> 772
    // Local variable table:
    //   start	length	slot	name	signature
    //   0	1255	0	this	dz
    //   166	1086	1	j	int
    //   246	120	2	l	long
    //   12	852	4	localObject1	Object
    //   868	9	4	localException1	Exception
    //   959	154	4	localObject2	Object
    //   1130	1	4	localJSONException	org.json.JSONException
    //   1188	1	4	localObject3	Object
    //   1198	6	4	localObject4	Object
    //   1206	9	4	localException2	Exception
    //   1240	1	4	localObject5	Object
    //   93	692	6	localcy	cy
    //   175	294	7	localObject7	Object
    //   182	935	8	localJSONArray	org.json.JSONArray
    //   207	963	9	str	String
    // Exception table:
    //   from	to	target	type
    //   0	52	868	java/lang/Exception
    //   52	80	868	java/lang/Exception
    //   88	102	868	java/lang/Exception
    //   107	114	868	java/lang/Exception
    //   119	132	868	java/lang/Exception
    //   137	160	868	java/lang/Exception
    //   171	184	868	java/lang/Exception
    //   193	259	868	java/lang/Exception
    //   264	272	868	java/lang/Exception
    //   272	282	868	java/lang/Exception
    //   282	371	868	java/lang/Exception
    //   376	389	868	java/lang/Exception
    //   389	397	868	java/lang/Exception
    //   403	426	868	java/lang/Exception
    //   686	710	868	java/lang/Exception
    //   710	718	868	java/lang/Exception
    //   724	762	868	java/lang/Exception
    //   762	770	868	java/lang/Exception
    //   776	800	868	java/lang/Exception
    //   800	836	868	java/lang/Exception
    //   837	865	868	java/lang/Exception
    //   932	943	868	java/lang/Exception
    //   948	958	868	java/lang/Exception
    //   964	994	868	java/lang/Exception
    //   997	1022	868	java/lang/Exception
    //   1022	1037	868	java/lang/Exception
    //   1040	1058	868	java/lang/Exception
    //   1061	1097	868	java/lang/Exception
    //   1112	1127	868	java/lang/Exception
    //   1132	1142	868	java/lang/Exception
    //   1145	1187	868	java/lang/Exception
    //   1200	1206	868	java/lang/Exception
    //   1208	1220	868	java/lang/Exception
    //   1223	1233	868	java/lang/Exception
    //   171	184	1130	org/json/JSONException
    //   193	259	1130	org/json/JSONException
    //   264	272	1130	org/json/JSONException
    //   272	282	1130	org/json/JSONException
    //   282	371	1130	org/json/JSONException
    //   376	389	1130	org/json/JSONException
    //   1112	1127	1130	org/json/JSONException
    //   1145	1187	1130	org/json/JSONException
    //   426	458	1198	finally
    //   458	468	1198	finally
    //   468	514	1206	java/lang/Exception
    //   514	548	1206	java/lang/Exception
    //   548	582	1206	java/lang/Exception
    //   582	686	1206	java/lang/Exception
  }
}

/* Location:
 * Qualified Name:     bo.app.dz
 * Java Class Version: 6 (50.0)
 * JD-Core Version:    0.7.1
 */