package bo.app;

public final class fp
  implements Runnable
{
  public fp(fo paramfo) {}
  
  /* Error */
  public final void run()
  {
    // Byte code:
    //   0: iconst_0
    //   1: istore_1
    //   2: aload_0
    //   3: getfield 12	bo/app/fp:a	Lbo/app/fo;
    //   6: invokestatic 27	bo/app/fo:b	(Lbo/app/fo;)Lbo/app/n;
    //   9: astore 4
    //   11: aload_0
    //   12: getfield 12	bo/app/fp:a	Lbo/app/fo;
    //   15: invokestatic 30	bo/app/fo:a	(Lbo/app/fo;)Lbo/app/ba;
    //   18: astore_2
    //   19: aload 4
    //   21: getfield 36	bo/app/n:e	Ljava/lang/Object;
    //   24: astore_3
    //   25: aload_3
    //   26: monitorenter
    //   27: aload 4
    //   29: iconst_0
    //   30: putfield 40	bo/app/n:h	Z
    //   33: aload 4
    //   35: getfield 44	bo/app/n:g	Ljava/lang/Thread;
    //   38: invokevirtual 49	java/lang/Thread:interrupt	()V
    //   41: aload 4
    //   43: aconst_null
    //   44: putfield 44	bo/app/n:g	Ljava/lang/Thread;
    //   47: aload_3
    //   48: monitorexit
    //   49: aload 4
    //   51: getfield 53	bo/app/n:d	Lbo/app/w;
    //   54: getfield 58	bo/app/w:a	Ljava/util/concurrent/LinkedBlockingQueue;
    //   57: invokevirtual 64	java/util/concurrent/LinkedBlockingQueue:isEmpty	()Z
    //   60: ifne +5 -> 65
    //   63: iconst_1
    //   64: istore_1
    //   65: iload_1
    //   66: ifne +29 -> 95
    //   69: aload 4
    //   71: getfield 53	bo/app/n:d	Lbo/app/w;
    //   74: new 66	bo/app/eb
    //   77: dup
    //   78: aload 4
    //   80: getfield 69	bo/app/n:b	Lcom/appboy/configuration/XmlAppConfigurationProvider;
    //   83: invokevirtual 75	com/appboy/configuration/XmlAppConfigurationProvider:getBaseUrlForRequests	()Ljava/lang/String;
    //   86: getstatic 80	bo/app/ab:e	I
    //   89: invokespecial 83	bo/app/eb:<init>	(Ljava/lang/String;I)V
    //   92: invokevirtual 86	bo/app/w:a	(Lbo/app/ee;)V
    //   95: aload 4
    //   97: getfield 90	bo/app/n:c	Lbo/app/eg;
    //   100: aload 4
    //   102: getfield 53	bo/app/n:d	Lbo/app/w;
    //   105: invokevirtual 93	bo/app/w:a	()Lbo/app/ee;
    //   108: invokeinterface 98 2 0
    //   113: aload_2
    //   114: getfield 101	bo/app/ba:e	Ljava/lang/Object;
    //   117: astore_3
    //   118: aload_3
    //   119: monitorenter
    //   120: aload_2
    //   121: getfield 104	bo/app/ba:b	Ljava/util/concurrent/ConcurrentMap;
    //   124: invokeinterface 109 1 0
    //   129: aload_3
    //   130: monitorexit
    //   131: aload_2
    //   132: getfield 112	bo/app/ba:f	Ljava/lang/Object;
    //   135: astore_3
    //   136: aload_3
    //   137: monitorenter
    //   138: aload_2
    //   139: getfield 114	bo/app/ba:c	Ljava/util/concurrent/ConcurrentMap;
    //   142: invokeinterface 109 1 0
    //   147: aload_3
    //   148: monitorexit
    //   149: aload_2
    //   150: getfield 116	bo/app/ba:d	Ljava/lang/Object;
    //   153: astore_3
    //   154: aload_3
    //   155: monitorenter
    //   156: aload_2
    //   157: getfield 118	bo/app/ba:a	Ljava/util/concurrent/ConcurrentMap;
    //   160: invokeinterface 109 1 0
    //   165: aload_3
    //   166: monitorexit
    //   167: aload_0
    //   168: getfield 12	bo/app/fp:a	Lbo/app/fo;
    //   171: invokestatic 121	bo/app/fo:c	(Lbo/app/fo;)Lbo/app/r;
    //   174: invokevirtual 125	bo/app/r:b	()Z
    //   177: pop
    //   178: aload_0
    //   179: getfield 12	bo/app/fp:a	Lbo/app/fo;
    //   182: invokestatic 128	bo/app/fo:d	(Lbo/app/fo;)Lbo/app/fa;
    //   185: invokevirtual 133	bo/app/fa:c	()Landroid/database/sqlite/SQLiteDatabase;
    //   188: invokevirtual 138	android/database/sqlite/SQLiteDatabase:close	()V
    //   191: return
    //   192: astore_2
    //   193: aload_3
    //   194: monitorexit
    //   195: aload_2
    //   196: athrow
    //   197: astore_2
    //   198: invokestatic 140	bo/app/fo:a	()Ljava/lang/String;
    //   201: ldc -114
    //   203: aload_2
    //   204: invokestatic 148	com/appboy/support/AppboyLogger:w	(Ljava/lang/String;Ljava/lang/String;Ljava/lang/Throwable;)I
    //   207: pop
    //   208: goto -41 -> 167
    //   211: astore_3
    //   212: getstatic 151	bo/app/n:a	Ljava/lang/String;
    //   215: ldc -103
    //   217: invokestatic 156	com/appboy/support/AppboyLogger:w	(Ljava/lang/String;Ljava/lang/String;)I
    //   220: pop
    //   221: goto -108 -> 113
    //   224: astore_2
    //   225: aload_3
    //   226: monitorexit
    //   227: aload_2
    //   228: athrow
    //   229: astore_2
    //   230: aload_3
    //   231: monitorexit
    //   232: aload_2
    //   233: athrow
    //   234: astore_2
    //   235: aload_3
    //   236: monitorexit
    //   237: aload_2
    //   238: athrow
    //   239: astore_2
    //   240: invokestatic 140	bo/app/fo:a	()Ljava/lang/String;
    //   243: ldc -98
    //   245: aload_2
    //   246: invokestatic 148	com/appboy/support/AppboyLogger:w	(Ljava/lang/String;Ljava/lang/String;Ljava/lang/Throwable;)I
    //   249: pop
    //   250: goto -72 -> 178
    //   253: astore_2
    //   254: invokestatic 140	bo/app/fo:a	()Ljava/lang/String;
    //   257: ldc -96
    //   259: aload_2
    //   260: invokestatic 148	com/appboy/support/AppboyLogger:w	(Ljava/lang/String;Ljava/lang/String;Ljava/lang/Throwable;)I
    //   263: pop
    //   264: return
    // Local variable table:
    //   start	length	slot	name	signature
    //   0	265	0	this	fp
    //   1	65	1	i	int
    //   18	139	2	localba	ba
    //   192	4	2	localObject1	Object
    //   197	7	2	localException1	Exception
    //   224	4	2	localObject2	Object
    //   229	4	2	localObject3	Object
    //   234	4	2	localObject4	Object
    //   239	7	2	localException2	Exception
    //   253	7	2	localException3	Exception
    //   211	25	3	localInterruptedException	InterruptedException
    //   9	92	4	localn	n
    // Exception table:
    //   from	to	target	type
    //   27	49	192	finally
    //   2	27	197	java/lang/Exception
    //   49	63	197	java/lang/Exception
    //   69	95	197	java/lang/Exception
    //   95	113	197	java/lang/Exception
    //   113	120	197	java/lang/Exception
    //   131	138	197	java/lang/Exception
    //   149	156	197	java/lang/Exception
    //   193	197	197	java/lang/Exception
    //   212	221	197	java/lang/Exception
    //   225	229	197	java/lang/Exception
    //   230	234	197	java/lang/Exception
    //   235	239	197	java/lang/Exception
    //   95	113	211	java/lang/InterruptedException
    //   120	131	224	finally
    //   138	149	229	finally
    //   156	167	234	finally
    //   167	178	239	java/lang/Exception
    //   178	191	253	java/lang/Exception
  }
}

/* Location:
 * Qualified Name:     bo.app.fp
 * Java Class Version: 6 (50.0)
 * JD-Core Version:    0.7.1
 */