package com.google.android.gms.internal;

import android.os.Binder;
import android.os.Bundle;
import android.os.IBinder;
import android.os.IInterface;
import android.os.Parcel;
import android.os.RemoteException;
import com.google.android.gms.dynamic.zzd;
import com.google.android.gms.dynamic.zzd.zza;
import java.util.ArrayList;
import java.util.List;

public abstract interface zzea
  extends IInterface
{
  public abstract void destroy()
    throws RemoteException;
  
  public abstract String getAdvertiser()
    throws RemoteException;
  
  public abstract String getBody()
    throws RemoteException;
  
  public abstract String getCallToAction()
    throws RemoteException;
  
  public abstract Bundle getExtras()
    throws RemoteException;
  
  public abstract String getHeadline()
    throws RemoteException;
  
  public abstract List getImages()
    throws RemoteException;
  
  public abstract zzd zzkx()
    throws RemoteException;
  
  public abstract zzdu zzla()
    throws RemoteException;
  
  public static abstract class zza
    extends Binder
    implements zzea
  {
    public zza()
    {
      attachInterface(this, "com.google.android.gms.ads.internal.formats.client.INativeContentAd");
    }
    
    public static zzea zzac(IBinder paramIBinder)
    {
      if (paramIBinder == null) {
        return null;
      }
      IInterface localIInterface = paramIBinder.queryLocalInterface("com.google.android.gms.ads.internal.formats.client.INativeContentAd");
      if ((localIInterface != null) && ((localIInterface instanceof zzea))) {
        return (zzea)localIInterface;
      }
      return new zza(paramIBinder);
    }
    
    public IBinder asBinder()
    {
      return this;
    }
    
    public boolean onTransact(int paramInt1, Parcel paramParcel1, Parcel paramParcel2, int paramInt2)
      throws RemoteException
    {
      zzd localzzd = null;
      zzdu localzzdu = null;
      switch (paramInt1)
      {
      default: 
        return super.onTransact(paramInt1, paramParcel1, paramParcel2, paramInt2);
      case 1598968902: 
        paramParcel2.writeString("com.google.android.gms.ads.internal.formats.client.INativeContentAd");
        return true;
      case 2: 
        paramParcel1.enforceInterface("com.google.android.gms.ads.internal.formats.client.INativeContentAd");
        localzzd = zzkx();
        paramParcel2.writeNoException();
        paramParcel1 = localzzdu;
        if (localzzd != null) {
          paramParcel1 = localzzd.asBinder();
        }
        paramParcel2.writeStrongBinder(paramParcel1);
        return true;
      case 3: 
        paramParcel1.enforceInterface("com.google.android.gms.ads.internal.formats.client.INativeContentAd");
        paramParcel1 = getHeadline();
        paramParcel2.writeNoException();
        paramParcel2.writeString(paramParcel1);
        return true;
      case 4: 
        paramParcel1.enforceInterface("com.google.android.gms.ads.internal.formats.client.INativeContentAd");
        paramParcel1 = getImages();
        paramParcel2.writeNoException();
        paramParcel2.writeList(paramParcel1);
        return true;
      case 5: 
        paramParcel1.enforceInterface("com.google.android.gms.ads.internal.formats.client.INativeContentAd");
        paramParcel1 = getBody();
        paramParcel2.writeNoException();
        paramParcel2.writeString(paramParcel1);
        return true;
      case 6: 
        paramParcel1.enforceInterface("com.google.android.gms.ads.internal.formats.client.INativeContentAd");
        localzzdu = zzla();
        paramParcel2.writeNoException();
        paramParcel1 = localzzd;
        if (localzzdu != null) {
          paramParcel1 = localzzdu.asBinder();
        }
        paramParcel2.writeStrongBinder(paramParcel1);
        return true;
      case 7: 
        paramParcel1.enforceInterface("com.google.android.gms.ads.internal.formats.client.INativeContentAd");
        paramParcel1 = getCallToAction();
        paramParcel2.writeNoException();
        paramParcel2.writeString(paramParcel1);
        return true;
      case 8: 
        paramParcel1.enforceInterface("com.google.android.gms.ads.internal.formats.client.INativeContentAd");
        paramParcel1 = getAdvertiser();
        paramParcel2.writeNoException();
        paramParcel2.writeString(paramParcel1);
        return true;
      case 9: 
        paramParcel1.enforceInterface("com.google.android.gms.ads.internal.formats.client.INativeContentAd");
        paramParcel1 = getExtras();
        paramParcel2.writeNoException();
        if (paramParcel1 != null)
        {
          paramParcel2.writeInt(1);
          paramParcel1.writeToParcel(paramParcel2, 1);
        }
        for (;;)
        {
          return true;
          paramParcel2.writeInt(0);
        }
      }
      paramParcel1.enforceInterface("com.google.android.gms.ads.internal.formats.client.INativeContentAd");
      destroy();
      paramParcel2.writeNoException();
      return true;
    }
    
    private static class zza
      implements zzea
    {
      private IBinder zzahn;
      
      zza(IBinder paramIBinder)
      {
        zzahn = paramIBinder;
      }
      
      public IBinder asBinder()
      {
        return zzahn;
      }
      
      public void destroy()
        throws RemoteException
      {
        Parcel localParcel1 = Parcel.obtain();
        Parcel localParcel2 = Parcel.obtain();
        try
        {
          localParcel1.writeInterfaceToken("com.google.android.gms.ads.internal.formats.client.INativeContentAd");
          zzahn.transact(10, localParcel1, localParcel2, 0);
          localParcel2.readException();
          return;
        }
        finally
        {
          localParcel2.recycle();
          localParcel1.recycle();
        }
      }
      
      public String getAdvertiser()
        throws RemoteException
      {
        Parcel localParcel1 = Parcel.obtain();
        Parcel localParcel2 = Parcel.obtain();
        try
        {
          localParcel1.writeInterfaceToken("com.google.android.gms.ads.internal.formats.client.INativeContentAd");
          zzahn.transact(8, localParcel1, localParcel2, 0);
          localParcel2.readException();
          String str = localParcel2.readString();
          return str;
        }
        finally
        {
          localParcel2.recycle();
          localParcel1.recycle();
        }
      }
      
      public String getBody()
        throws RemoteException
      {
        Parcel localParcel1 = Parcel.obtain();
        Parcel localParcel2 = Parcel.obtain();
        try
        {
          localParcel1.writeInterfaceToken("com.google.android.gms.ads.internal.formats.client.INativeContentAd");
          zzahn.transact(5, localParcel1, localParcel2, 0);
          localParcel2.readException();
          String str = localParcel2.readString();
          return str;
        }
        finally
        {
          localParcel2.recycle();
          localParcel1.recycle();
        }
      }
      
      public String getCallToAction()
        throws RemoteException
      {
        Parcel localParcel1 = Parcel.obtain();
        Parcel localParcel2 = Parcel.obtain();
        try
        {
          localParcel1.writeInterfaceToken("com.google.android.gms.ads.internal.formats.client.INativeContentAd");
          zzahn.transact(7, localParcel1, localParcel2, 0);
          localParcel2.readException();
          String str = localParcel2.readString();
          return str;
        }
        finally
        {
          localParcel2.recycle();
          localParcel1.recycle();
        }
      }
      
      /* Error */
      public Bundle getExtras()
        throws RemoteException
      {
        // Byte code:
        //   0: invokestatic 30	android/os/Parcel:obtain	()Landroid/os/Parcel;
        //   3: astore_2
        //   4: invokestatic 30	android/os/Parcel:obtain	()Landroid/os/Parcel;
        //   7: astore_3
        //   8: aload_2
        //   9: ldc 32
        //   11: invokevirtual 36	android/os/Parcel:writeInterfaceToken	(Ljava/lang/String;)V
        //   14: aload_0
        //   15: getfield 18	com/google/android/gms/internal/zzea$zza$zza:zzahn	Landroid/os/IBinder;
        //   18: bipush 9
        //   20: aload_2
        //   21: aload_3
        //   22: iconst_0
        //   23: invokeinterface 42 5 0
        //   28: pop
        //   29: aload_3
        //   30: invokevirtual 45	android/os/Parcel:readException	()V
        //   33: aload_3
        //   34: invokevirtual 62	android/os/Parcel:readInt	()I
        //   37: ifeq +26 -> 63
        //   40: getstatic 68	android/os/Bundle:CREATOR	Landroid/os/Parcelable$Creator;
        //   43: aload_3
        //   44: invokeinterface 74 2 0
        //   49: checkcast 64	android/os/Bundle
        //   52: astore_1
        //   53: aload_3
        //   54: invokevirtual 48	android/os/Parcel:recycle	()V
        //   57: aload_2
        //   58: invokevirtual 48	android/os/Parcel:recycle	()V
        //   61: aload_1
        //   62: areturn
        //   63: aconst_null
        //   64: astore_1
        //   65: goto -12 -> 53
        //   68: astore_1
        //   69: aload_3
        //   70: invokevirtual 48	android/os/Parcel:recycle	()V
        //   73: aload_2
        //   74: invokevirtual 48	android/os/Parcel:recycle	()V
        //   77: aload_1
        //   78: athrow
        // Local variable table:
        //   start	length	slot	name	signature
        //   0	79	0	this	zza
        //   52	13	1	localBundle	Bundle
        //   68	10	1	localObject	Object
        //   3	71	2	localParcel1	Parcel
        //   7	63	3	localParcel2	Parcel
        // Exception table:
        //   from	to	target	type
        //   8	53	68	finally
      }
      
      public String getHeadline()
        throws RemoteException
      {
        Parcel localParcel1 = Parcel.obtain();
        Parcel localParcel2 = Parcel.obtain();
        try
        {
          localParcel1.writeInterfaceToken("com.google.android.gms.ads.internal.formats.client.INativeContentAd");
          zzahn.transact(3, localParcel1, localParcel2, 0);
          localParcel2.readException();
          String str = localParcel2.readString();
          return str;
        }
        finally
        {
          localParcel2.recycle();
          localParcel1.recycle();
        }
      }
      
      public List getImages()
        throws RemoteException
      {
        Parcel localParcel1 = Parcel.obtain();
        Parcel localParcel2 = Parcel.obtain();
        try
        {
          localParcel1.writeInterfaceToken("com.google.android.gms.ads.internal.formats.client.INativeContentAd");
          zzahn.transact(4, localParcel1, localParcel2, 0);
          localParcel2.readException();
          ArrayList localArrayList = localParcel2.readArrayList(getClass().getClassLoader());
          return localArrayList;
        }
        finally
        {
          localParcel2.recycle();
          localParcel1.recycle();
        }
      }
      
      public zzd zzkx()
        throws RemoteException
      {
        Parcel localParcel1 = Parcel.obtain();
        Parcel localParcel2 = Parcel.obtain();
        try
        {
          localParcel1.writeInterfaceToken("com.google.android.gms.ads.internal.formats.client.INativeContentAd");
          zzahn.transact(2, localParcel1, localParcel2, 0);
          localParcel2.readException();
          zzd localzzd = zzd.zza.zzfc(localParcel2.readStrongBinder());
          return localzzd;
        }
        finally
        {
          localParcel2.recycle();
          localParcel1.recycle();
        }
      }
      
      public zzdu zzla()
        throws RemoteException
      {
        Parcel localParcel1 = Parcel.obtain();
        Parcel localParcel2 = Parcel.obtain();
        try
        {
          localParcel1.writeInterfaceToken("com.google.android.gms.ads.internal.formats.client.INativeContentAd");
          zzahn.transact(6, localParcel1, localParcel2, 0);
          localParcel2.readException();
          zzdu localzzdu = zzdu.zza.zzy(localParcel2.readStrongBinder());
          return localzzdu;
        }
        finally
        {
          localParcel2.recycle();
          localParcel1.recycle();
        }
      }
    }
  }
}

/* Location:
 * Qualified Name:     com.google.android.gms.internal.zzea
 * Java Class Version: 6 (50.0)
 * JD-Core Version:    0.7.1
 */